Workbook
Name nrGeneratedAt: 'Dashboard'!$A$2
Name nrReviewOpenCount: 'TemplateInfo'!$B$2
Name nrReviewDeferredCount: 'TemplateInfo'!$B$3
Name nrReviewResolvedCount: 'TemplateInfo'!$B$4
Name nrCampaignActionCount: 'TemplateInfo'!$B$5
Name nrCampaignRepoCount: 'TemplateInfo'!$B$6
Name nrGovernanceReadyCount: 'TemplateInfo'!$B$7
Name nrGovernanceDriftCount: 'TemplateInfo'!$B$8
Name nrPortfolioGrade: 'TemplateInfo'!$B$9
Name nrAverageScore: 'TemplateInfo'!$B$10
Name nrLatestReviewState: 'TemplateInfo'!$B$11
Name nrSelectedProfileLabel: 'TemplateInfo'!$B$12
Name nrSelectedCollectionLabel: 'TemplateInfo'!$B$13

Sheet Index
A1: GitHub Portfolio Audit: sample-user | J1: Quick Links
A2: Last updated: 2026-04-12 | 3 repos | Grade: B | J2: Dashboard
A3: Use this workbook in order: Dashboard for the brief, Run Changes for movement, Review Queue for action, Repo Detail for one-repo context, and Executive Summary for a shareable recap. | J3: Review Queue
A4: Start Here | J4: Repo Detail
A5: Workbook Mode | B5: standard | C5: Profile | D5: default | J5: Run Changes
A6: Collection | B6: all | C6: Source Run | D6: sample-user:2026-04-12T12:00:00+00:00 | J6: Executive Summary
A7: Report Reference | C7: Operator Headline | D7: RepoC still needs security follow-through before the queue will calm down.
A8: Next Run | B8: incremental | C8: Watch Strategy | D8: adaptive
A9: The current baseline is still compatible, so incremental watch remains safe for the next run.
A10: What changed: RepoC drift needs review and RepoB reopened a release checklist item.
A11: Why it matters: Live drift is still present, so security work should stay ahead of lower-pressure cleanup.
A12: What to do next: Review RepoC first, then close RepoB's reopened checklist item.
A13: Follow-through: One urgent item is still repeating in the recent window.
A14: Escalation: No stronger follow-through escalation is currently surfaced.
A15: Start with Dashboard for the portfolio brief, move to Review Queue for action, then drill into Portfolio Explorer and Executive Summary for detail.
A16: Operating rules: standard mode is the default path, visible sheets stay filter-based, and hidden Data_* sheets remain the workbook contract. Advanced sheets are hidden by default; use Excel Unhide when you need deeper diagnostics.
E17: Portfolio Analysis
A18: Daily Triage | E18: Sheet | F18: Use This When | G18: Go
A19: Sheet | B19: Use This When | C19: Go | E19: Portfolio Explorer | F19: Rank repos, compare score quality, and drill from summary into raw facts. | G19: Open
A20: Dashboard | B20: Start here for the big-picture health view and top attention items. | C20: Open | E20: Repo Detail | F20: Select one repo and get a single-page briefing on score, risks, trend, and next action. | G20: Open
A21: Review Queue | B21: Use this for blocked, urgent, ready, and safe-to-defer review work. | C21: Open | E21: By Lens | F21: Compare the portfolio by ship readiness, momentum, security, and fit. | G21: Open
A22: Run Changes | B22: See what changed since the last run before you decide where to spend attention. | C22: Open | E22: By Collection | F22: Understand collection-level leaders and concentration. | G22: Open
A23: Campaigns | B23: Check managed campaign state, reopen/closure context, and drift. | C23: Open | E23: Trend Summary | F23: See portfolio-wide movement and repo trendlines over time. | G23: Open
A24: Governance Controls | B24: Review governed controls, approval posture, and rollback visibility. | C24: Open | E24: All Repos | F24: Scan the full inventory with grades, tiers, and supporting evidence. | G24: Open
A25: Writeback Audit | B25: See what writeback changed and what is reversible. | C25: Open
A27: Executive Readout | E27: Deep Diagnostics
A28: Sheet | B28: Use This When | C28: Go | E28: Sheet | F28: Use This When | G28: Go
A29: Executive Summary | B29: Readable leadership summary with what changed and what matters this week. | C29: Open | E29: Security | F29: Raw security posture, secrets, and dangerous-file findings. | G29: Open
A30: Print Pack | B30: Print-friendly handoff with risks, opportunities, and operator counts in plain language. | C30: Open | E30: Security Controls | F30: Control coverage and rollout detail by repo. | G30: Open
E31: Supply Chain | F31: Dependency health, scorecard signals, and provider coverage. | G31: Open
E32: Scoring Heatmap | F32: Dimension-by-dimension matrix for detailed score inspection. | G32: Open
E33: Hotspots | F33: Highest-severity risks and opportunities across the portfolio. | G33: Open
E34: Review History | F34: Recurring review history and decision-state ledger. | G34: Open
E35: Governance Audit | F35: Approval, drift, and rollback evidence summary. | G35: Open
E36: Score Explainer | F36: How scores, grades, and tiers are computed. | G36: Open
E37: Action Items | F37: Prioritized improvement ideas with effort context. | G37: Open

Sheet Dashboard
A1: GitHub Portfolio Dashboard: sample-user | AO1: Quick Links
A2: Generated: 2026-04-12 | 3 repos audited | AO2: Dashboard
A3: Since last audit (2026-04-05): | avg score +0.020 | 2 tier changes | Priority: RepoC needs 0.110 to promote | AO3: Review Queue
A4: Portfolio Health Snapshot | O4: Operator Attention Snapshot | AO4: Repo Detail
A5: Portfolio Grade | C5: Avg Score | E5: Shipped | G5: Functional | I5: WIP | K5: Needs Work | O5: Operator Snapshot | AO5: Run Changes
A6: B | C6: 0.65 | E6: 1 | G6: 1 | I6: 1 | K6: 0 | O6: Setup Health | P6: Ok | AO6: Executive Summary
O7: Operator Headline | P7: RepoC still needs security follow-through before the queue will calm down.
A8: Portfolio DNA | M8: Run Summary | N8: Average score moved +0.020; 0 meaningful improvements, 0 regressions, 1 promotions, and 1 demotions were recorded. | O8: Queue Counts | P8: 1 blocked, 1 urgent, 1 ready, 1 deferred
A9: Use the left side for portfolio shape and the right side for operator pressure. If you only have a minute, read the narrative, scan the queue snapshot, and then open Review Queue. | M9: Queue Pressure | N9: 1 blocked, 1 urgent, 1 ready, and 1 deferred item(s) are currently in the queue. | O9: Governance | P9: Governed security drift needs review.
M10: Trust Summary | N10: verify-first — The recommendation is sound, but recent reopen noise means it should still be reviewed before acting. | O10: Campaign State | P10: Security Review | X10: Shipped | Y10: 1 | AA10: A | AB10: 1 | AD10: Python | AE10: 2 | AG10: RepoA | AH10: 0.88 | AI10: 0.61 | AJ10: 0.55 | AK10: 0 | AL10: 0 | AM10: 0.45
M11: Top Recommendation | N11: Review RepoC first, then close RepoB's reopened checklist item. Start with RepoC if you need a concrete place to begin. | O11: Run Changes | P11: Average score moved +0.020; 0 meaningful improvements, 0 regressions, 1 promotions, and 1 demotions were recorded. | X11: Functional | Y11: 1 | AA11: B | AB11: 0 | AD11: TypeScript | AE11: 1 | AG11: RepoB | AH11: 0.62 | AI11: 0.37 | AJ11: 0.55 | AK11: 1 | AL11: 1 | AM11: 0.45
M12: Use This Page | N12: Read the left side for portfolio shape, the right side for operator pressure, then jump into Review Queue or Repo Detail. | O12: Queue Pressure | P12: 1 blocked, 1 urgent, 1 ready, and 1 deferred item(s) are currently in the queue. | X12: Wip | Y12: 1 | AA12: C | AB12: 1 | AG12: RepoC | AH12: 0.44 | AI12: 0.16
O13: What Changed | P13: RepoC drift needs review and RepoB reopened a release checklist item. | X13: Skeleton | Y13: 0 | AA13: D | AB13: 1
O14: Why It Matters | P14: Live drift is still present, so security work should stay ahead of lower-pressure cleanup. | X14: Abandoned | Y14: 0 | AA14: F | AB14: 0
O15: Follow-Through | P15: One urgent item is still repeating in the recent window.
O16: Next Checkpoint | P16: Use the next run or linked artifact to confirm whether the recommendation moved.
O17: Escalation | P17: No stronger follow-through escalation is currently surfaced.
O18: Recovery / Retirement | P18: No follow-through recovery or escalation-retirement signal is currently surfaced.
O19: Recovery Persistence | P19: No follow-through recovery persistence signal is currently surfaced.
O20: Relapse Churn | P20: No relapse churn is currently surfaced.
O21: Recovery Freshness | P21: No follow-through recovery freshness signal is currently surfaced.
O22: Recovery Memory Reset | P22: No follow-through recovery memory reset signal is currently surfaced.
O23: Recovery Rebuild Strength | P23: No follow-through recovery rebuild-strength signal is currently surfaced.
O24: Recovery Reacquisition | P24: No follow-through recovery reacquisition signal is currently surfaced.
O25: Reacquisition Durability | P25: No follow-through reacquisition durability signal is currently surfaced.
O26: Reacquisition Confidence | P26: No follow-through reacquisition confidence-consolidation signal is currently surfaced.
... O30: Portfolio Catalog | P30: No portfolio catalog contract is recorded yet.
A31: Highlights | O31: Operating Paths | P31: No normalized operating-path contract is recorded yet.
O32: Intent Alignment | P32: Intent alignment cannot be judged until a portfolio catalog contract exists.
O33: Scorecards | P33: No maturity scorecard is recorded yet.
O34: Next Action | P34: Review RepoC first, then close RepoB's reopened checklist item.
O35: Top Recommendation | P35: Review RepoC first, then close RepoB's reopened checklist item. Start with RepoC if you need a concrete place to begin.
O36: Trend | P36: Stable — Queue pressure is stable but still sticky.
O37: Primary Target | P37: No active target
O38: Resolution Counts | P38: New 0 | Resolved 0 | Persisting 0
O39: Recovery Hotspot | P39: No active recovery or retirement hotspot
O40: Retiring Watch Hotspot | P40: No active recovery or retirement hotspot
O41: Churn Hotspot | P41: No relapse-churn hotspot
O42: Freshness Hotspot | P42: No stale recovery-memory hotspot
O43: Freshness Detail | P43: No follow-through recovery freshness signal is currently surfaced.
... O51: Durable Reacquired Hotspot | P51: No durable re-acquisition hotspot
J52: Scatter Quadrants | O52: Softening Reacquired Hotspot | P52: No softening re-acquisition hotspot
J53: Quadrant | K53: Count | L53: Repos | O53: Fragile Reacquisition Confidence Hotspot | P53: No fragile re-acquisition confidence hotspot
J54: Flagships | K54: 1 | L54: RepoA | O54: Reacquisition Softening Hotspot | P54: No reacquisition softening hotspot
J55: Hidden Gems | K55: 0 | O55: Revalidation Needed Hotspot | P55: No reacquisition revalidation hotspot
J56: Workhorses | K56: 1 | L56: RepoB | O56: Retired Confidence Hotspot | P56: No retired re-acquisition confidence hotspot
J57: Archive Candidates | K57: 1 | L57: RepoC | O57: Under Revalidation Hotspot | P57: No under-revalidation recovery hotspot
O58: Rebuilding Restored Confidence Hotspot | P58: No rebuilding restored-confidence hotspot
O59: Re-Earning Confidence Hotspot | P59: No confidence re-earning hotspot
O60: Just Re-Earned Confidence Hotspot | P60: No just re-earned confidence hotspot
O61: Holding Re-Earned Confidence Hotspot | P61: No holding re-earned confidence hotspot
O62: Next Run | P62: incremental
O63: Watch Strategy | P63: adaptive
O64: Watch Decision | P64: The current baseline is still compatible, so incremental watch remains safe for the next run.
O65: Source Run | P65: sample-user:2026-04-12T12:00:00+00:00
O66: Why Top Target | P66: RepoC remains the top target because live drift is still open.
O67: Follow-Through Hotspot | P67: No outstanding follow-through hotspot
O68: Escalation Hotspot | P68: No outstanding follow-through hotspot
O69: Recovery Hotspot | P69: No active recovery or retirement hotspot
... O112: Reopened Recommendations | P112: 0 reopened
O114: Top Attention Items
O115: Repo | P115: Counts | Q115: Why Now | R115: Next Step
O116: RepoC | P116: B1 / U0 / R0 | Q116: Security drift needs review | R116: Open the governed control preview and decide whether to apply CodeQL.
O117: RepoB | P117: B0 / U1 / R0 | Q117: Release checklist reopened | R117: Re-run the release checklist and close the missing item.
O118: RepoA | P118: B0 / U0 / R1 | Q118: Archive old brainstorm notes | R118: Leave this alone unless priorities change.
O122: Top Opportunities
O123: Repo | P123: Score | Q123: Tier | R123: Best Next Move
O124: RepoA | P124: 0.88 | Q124: shipped | R124: Publish the next maintenance release
O125: RepoB | P125: 0.62 | Q125: functional | R125: Close the reopened release item
O126: RepoC | P126: 0.44 | Q126: wip | R126: Preview governance controls
O130: Top Laggards
O131: Repo | P131: Score | Q131: Tier | R131: What Is Dragging It Down
O132: RepoC | P132: 0.44 | Q132: wip | R132: Security posture needs attention
O133: RepoB | P133: 0.62 | Q133: functional | R133: Finish release checklist
O134: RepoA | P134: 0.88 | Q134: shipped | R134: Keep release notes fresh

Sheet Review Queue
A1: Review Queue | AQ1: Quick Links
A2: Start with the summary strip, then use the full queue below when you need row-level facts and decision context. | AQ2: Dashboard
A3: Work this page in lane order: clear Blocked first, handle Needs Attention Now next, and only then move into Ready for Manual Action or Safe to Defer. | AQ3: Review Queue
A4: Summary | E4: Top 10 To Act On | AQ4: Repo Detail
A5: Headline | B5: RepoC still needs security follow-through before the queue will calm down. | E5: Repo | F5: Primary Lane | G5: Counts | H5: Why Now | I5: Next Step | AQ5: Run Changes
A6: Queue Counts | B6: 1 blocked, 1 urgent, 1 ready, 1 deferred | E6: RepoC | F6: Blocked | G6: 1 blocked, 0 urgent, 0 ready, 0 deferred | H6: Security drift needs review | I6: Open the governed control preview and decide whether to apply CodeQL. | AQ6: Executive Summary
A7: Queue Pressure | B7: 1 blocked, 1 urgent, 1 ready, and 1 deferred item(s) are currently in the queue. | E7: RepoB | F7: Needs Attention Now | G7: 0 blocked, 1 urgent, 0 ready, 0 deferred | H7: Release checklist reopened | I7: Re-run the release checklist and close the missing item.
A8: Total Queue Items | B8: 4 | E8: RepoA | F8: Ready for Manual Action | G8: 0 blocked, 0 urgent, 1 ready, 1 deferred | H8: Archive old brainstorm notes | I8: Leave this alone unless priorities change.
A9: Immediate Focus | B9: Open the governed control preview and decide whether to apply CodeQL.
A10: Top Recommendation | B10: Review RepoC first, then close RepoB's reopened checklist item.
A11: Top Issue Family | B11: Security Change (1)
A12: Trend | B12: Stable — Queue pressure is stable but still sticky.
A13: Primary Target | B13: No active target
A14: Resolution Counts | B14: New 0 | Resolved 0 | Persisting 0
A15: Why Top Target | B15: RepoC remains the top target because live drift is still open.
A16: Closure Guidance | B16: Clear RepoC's security drift before moving to lower-pressure work.
A17: Aging Pressure | B17: Chronic 0 | Newly stale 0 | Longest No persisting item
A18: What We Tried | B18: No recent intervention recorded
A19: Last Outcome | B19: No Change
A20: Resolution Evidence | B20: No resolution evidence is recorded yet.
... A58: Source Run | B58: sample-user:2026-04-12T12:00:00+00:00
A60: Top Issue Families | E60: Top Recommended Actions
A61: Issue Family | B61: Count | E61: Action | F61: Count
A62: Security Change | B62: 1 | E62: Open the governed control preview and decide whether to apply CodeQL. | F62: 1
A63: Reopened Review | B63: 1 | E63: Re-run the release checklist and close the missing item. | F63: 1
E64: Tidy the release notes and publish the next small maintenance release. | F64: 1
E65: Leave this alone unless priorities change. | F65: 1
A67: Read this table top-down: urgent items first, ready items second, and safe-to-defer rows last.
A68: Repo | B68: Title | C68: Lane | D68: Kind | E68: Priority | F68: Why This Is Here | G68: What To Do Next | H68: Catalog | I68: Operating Path | J68: Intent Alignment | K68: Maturity | L68: Scorecard Gap | M68: Last Movement | N68: Follow-Through | O68: Next Checkpoint | P68: Checkpoint Timing | Q68: Escalation | R68: Escalation Summary | S68: Recovery / Retirement | T68: Recovery Summary | U68: Recovery Persistence | V68: Persistence Summary | W68: Relapse Churn | X68: Churn Summary | Y68: Recovery Freshness | Z68: Freshness Summary | AA68: Recovery Memory Reset | AB68: Reset Summary | AC68: Recovery Rebuild Strength | AD68: Rebuild Summary | AE68: Recovery Reacquisition | AF68: Reacquisition Summary | AG68: Reacquisition Durability | AH68: Durability Summary | AI68: Reacquisition Confidence | AJ68: Confidence Summary | AK68: Operator Focus | AL68: Focus Summary | AM68: Focus Line | AN68: Open Artifact | AO68: Safe To Defer
A69: RepoC | B69: Security drift needs review | C69: blocked | D69: campaign | E69: 1 | F69: Governed security drift is still unresolved. | G69: Open the governed control preview and decide whether to apply CodeQL. | H69: No portfolio catalog contract is recorded yet. | I69: Operating Path: Unspecified (legacy confidence) — No operating-path rationale is recorded yet. | J69: missing-contract — Intent alignment cannot be judged until a portfolio catalog contract exists. | K69: — | L69: No maturity gap summary is recorded yet. | M69: Current run | N69: No follow-through evidence is recorded yet. | O69: Use the next run or linked artifact to confirm whether the recommendation moved. | P69: Unknown | Q69: Unknown | R69: No stronger follow-through escalation is currently surfaced. | S69: None | T69: No follow-through recovery or escalation-retirement signal is currently surfaced. | U69: None | V69: No follow-through recovery persistence signal is currently surfaced. | W69: None | X69: No relapse churn is currently surfaced. | Y69: None | Z69: No follow-through recovery freshness signal is currently surfaced. | AA69: None | AB69: No follow-through recovery memory reset signal is currently surfaced. | AC69: None | AD69: No follow-through recovery rebuild-strength signal is currently surfaced. | AE69: None | AF69: No follow-through recovery reacquisition signal is currently surfaced. | AG69: None | AH69: No follow-through reacquisition durability signal is currently surfaced. | AI69: None | AJ69: No follow-through reacquisition confidence-consolidation signal is currently surfaced. | AK69: Act Now | AL69: Governed security drift is still unresolved. | AM69: Act Now: Governed security drift is still unresolved. | AN69: Open linked artifact | AO69: no
A70: RepoB | B70: Release checklist reopened | C70: urgent | D70: review | E70: 2 | F70: A previously quiet repo reopened a visible checklist item. | G70: Re-run the release checklist and close the missing item. | H70: No portfolio catalog contract is recorded yet. | I70: Operating Path: Unspecified (legacy confidence) — No operating-path rationale is recorded yet. | J70: missing-contract — Intent alignment cannot be judged until a portfolio catalog contract exists. | K70: — | L70: No maturity gap summary is recorded yet. | M70: Current run | N70: No follow-through evidence is recorded yet. | O70: Use the next run or linked artifact to confirm whether the recommendation moved. | P70: Unknown | Q70: Unknown | R70: No stronger follow-through escalation is currently surfaced. | S70: None | T70: No follow-through recovery or escalation-retirement signal is currently surfaced. | U70: None | V70: No follow-through recovery persistence signal is currently surfaced. | W70: None | X70: No relapse churn is currently surfaced. | Y70: None | Z70: No follow-through recovery freshness signal is currently surfaced. | AA70: None | AB70: No follow-through recovery memory reset signal is currently surfaced. | AC70: None | AD70: No follow-through recovery rebuild-strength signal is currently surfaced. | AE70: None | AF70: No follow-through recovery reacquisition signal is currently surfaced. | AG70: None | AH70: No follow-through reacquisition durability signal is currently surfaced. | AI70: None | AJ70: No follow-through reacquisition confidence-consolidation signal is currently surfaced. | AK70: Act Now | AL70: A previously quiet repo reopened a visible checklist item. | AM70: Act Now: A previously quiet repo reopened a visible checklist item. | AN70: No linked artifact available yet. | AO70: no
A71: RepoA | B71: Protect shipped momentum | C71: ready | D71: maintenance | E71: 3 | F71: RepoA is healthy enough that a small polish task would keep it strong. | G71: Tidy the release notes and publish the next small maintenance release. | H71: No portfolio catalog contract is recorded yet. | I71: Operating Path: Unspecified (legacy confidence) — No operating-path rationale is recorded yet. | J71: missing-contract — Intent alignment cannot be judged until a portfolio catalog contract exists. | K71: — | L71: No maturity gap summary is recorded yet. | M71: Current run | N71: No follow-through evidence is recorded yet. | O71: Use the next run or linked artifact to confirm whether the recommendation moved. | P71: Unknown | Q71: Unknown | R71: No stronger follow-through escalation is currently surfaced. | S71: None | T71: No follow-through recovery or escalation-retirement signal is currently surfaced. | U71: None | V71: No follow-through recovery persistence signal is currently surfaced. | W71: None | X71: No relapse churn is currently surfaced. | Y71: None | Z71: No follow-through recovery freshness signal is currently surfaced. | AA71: None | AB71: No follow-through recovery memory reset signal is currently surfaced. | AC71: None | AD71: No follow-through recovery rebuild-strength signal is currently surfaced. | AE71: None | AF71: No follow-through recovery reacquisition signal is currently surfaced. | AG71: None | AH71: No follow-through reacquisition durability signal is currently surfaced. | AI71: None | AJ71: No follow-through reacquisition confidence-consolidation signal is currently surfaced. | AK71: Watch Closely | AL71: No follow-through evidence is recorded yet. | AM71: Watch Closely: No follow-through evidence is recorded yet. | AN71: No linked artifact available yet. | AO71: no
A72: RepoA | B72: Archive old brainstorm notes | C72: deferred | D72: cleanup | E72: 4 | F72: This is cleanup-only work with no current pressure. | G72: Leave this alone unless priorities change. | H72: No portfolio catalog contract is recorded yet. | I72: Operating Path: Unspecified (legacy confidence) — No operating-path rationale is recorded yet. | J72: missing-contract — Intent alignment cannot be judged until a portfolio catalog contract exists. | K72: — | L72: No maturity gap summary is recorded yet. | M72: Current run | N72: No follow-through evidence is recorded yet. | O72: Use the next run or linked artifact to confirm whether the recommendation moved. | P72: Unknown | Q72: Unknown | R72: No stronger follow-through escalation is currently surfaced. | S72: None | T72: No follow-through recovery or escalation-retirement signal is currently surfaced. | U72: None | V72: No follow-through recovery persistence signal is currently surfaced. | W72: None | X72: No relapse churn is currently surfaced. | Y72: None | Z72: No follow-through recovery freshness signal is currently surfaced. | AA72: None | AB72: No follow-through recovery memory reset signal is currently surfaced. | AC72: None | AD72: No follow-through recovery rebuild-strength signal is currently surfaced. | AE72: None | AF72: No follow-through recovery reacquisition signal is currently surfaced. | AG72: None | AH72: No follow-through reacquisition durability signal is currently surfaced. | AI72: None | AJ72: No follow-through reacquisition confidence-consolidation signal is currently surfaced. | AK72: Watch Closely | AL72: No follow-through evidence is recorded yet. | AM72: Watch Closely: No follow-through evidence is recorded yet. | AN72: No linked artifact available yet. | AO72: yes

Sheet Portfolio Explorer
A1: Portfolio Explorer | R1: Quick Links
A2: Use this sheet to rank the portfolio, sort by profile-aware score, and drill from summary into repo-level facts. | R2: Dashboard
A3: How to use this sheet: sort by Profile Score first, then use the catalog columns to separate intentional experiments from maintained assets before drilling in. | R3: Review Queue
R4: Repo Detail
A5: Repo | B5: Profile Score | C5: Overall | D5: Interest | E5: Tier | F5: Collections | G5: Lifecycle | H5: Criticality | I5: Disposition | J5: Operating Path | K5: Maturity | L5: Scorecard Gap | M5: Security | N5: Hotspots | O5: Top Hotspot | P5: Primary Action | R5: Run Changes
A6: RepoA | B6: 0.88 | C6: 0.88 | D6: 0.61 | E6: shipped | F6: showcase | G6: — | H6: — | I6: — | J6: — | K6: — | L6: No maturity gap summary is recorded yet. | M6: healthy | N6: 1 | O6: Keep release notes fresh | P6: Publish the next maintenance release | R6: Executive Summary
A7: RepoB | B7: 0.62 | C7: 0.62 | D7: 0.37 | E7: functional | G7: — | H7: — | I7: — | J7: — | K7: — | L7: No maturity gap summary is recorded yet. | M7: watch | N7: 1 | O7: Finish release checklist | P7: Close the reopened release item
A8: RepoC | B8: 0.44 | C8: 0.44 | D8: 0.16 | E8: wip | G8: — | H8: — | I8: — | J8: — | K8: — | L8: No maturity gap summary is recorded yet. | M8: critical | N8: 1 | O8: Security posture needs attention | P8: Preview governance controls

Sheet Implementation Hotspots
A1: Implementation Hotspots
A2: No meaningful implementation hotspots are currently surfaced.
A4: Repo | B4: Scope | C4: Path | D4: Module | E4: Category | F4: Pressure | G4: Suggestion | H4: Why It Matters | I4: Suggested First Move

Sheet Operator Outcomes
A1: Operator Outcomes
A2: Not enough operator history is recorded yet to judge outcomes.
A3: Not enough judged recommendation history is recorded yet to judge operator effectiveness.
A4: High-pressure queue trend is not ready yet.
A5: No recent Action Sync apply needs post-apply monitoring yet, so the local weekly story can stay local.
A6: Stay local for now; no recent Action Sync apply needs post-apply follow-up yet.
A7: Campaign tuning is neutral because there is not enough outcome history yet to bias tied recommendations.
A8: No current campaign needs a tuning tie-break yet.
A9: Automation guidance stays quiet until a campaign has a clearly safe preview, follow-up, or manual-only posture.
A10: Stay local for now; no current campaign has a stronger safe automation posture than manual review.
A11: No current approval needs review yet, so the approval workflow can stay local for now.
A12: Stay local for now; no current approval needs review.
A14: Metric | B14: Status | C14: Value | D14: Numerator | E14: Denominator | F14: Summary
A15: Review To Action Closure Rate | B15: insufficient-evidence
A16: Median Runs To Quiet After Escalation | B16: insufficient-evidence
A17: Repeated Regression Rate | B17: insufficient-evidence
A18: Recommendation Validation Rate | B18: insufficient-evidence
A19: Noisy Guidance Rate | B19: insufficient-evidence
A22: Post-Apply Monitoring
A23: Campaign | B23: State | C23: Pressure Effect | D23: Drift | E23: Reopen | F23: Summary
A30: Recent Examples
A31: Closed Actions | B31: No recent examples are recorded yet.
A32: Reopened Recommendations | B32: No recent examples are recorded yet.
A33: Regression Examples | B33: No recent examples are recorded yet.
A36: Run | B36: Generated | C36: Blocked | D36: Urgent | E36: High Pressure

Sheet Approval Ledger
A1: Approval Ledger
A2: No current approval needs review yet, so the approval workflow can stay local for now.
A3: Stay local for now; no current approval needs review.
A5: Label | B5: State | C5: Follow-Up | D5: Subject | E5: Reviewer | F5: Approved At | G5: Next Follow-Up Due | H5: Summary
A6: Needs Re-Approval
A7: None
A8: Overdue Follow-Up
A9: None
A10: Ready For Review
A11: None
A12: Due Soon Follow-Up
A13: None
A14: Approved But Manual
A15: None
A16: Blocked
A17: None

Sheet Historical Intelligence
A1: Historical Portfolio Intelligence
A2: Historical portfolio intelligence is still thin, so the weekly story should stay grounded in the current run and recent operator queue.
A3: Stay local for now; no repo has enough cross-run intervention evidence to demand a historical follow-up read yet.
A5: Repo | B5: Status | C5: Pressure Trend | D5: Hotspot Persistence | E5: Scorecard Trend | F5: Summary
A6: Relapsing
A7: No repos currently show a relapsing story.
A9: Persistent Pressure
A10: No repos currently show a persistent pressure story.
A12: Improving After Intervention
A13: No repos currently show a improving after intervention story.
A15: Holding Steady
A16: No repos currently show a holding steady story.

Sheet Repo Detail
A1: Repo Detail | L1: Quick Links
A2: Pick one repo, then use this page as the fastest single-repo briefing: score, tier, trend, risks, and next move. | L2: Dashboard
A3: Choose one repo, skim the briefing blocks top to bottom, then jump to Run Changes or Review Queue if you need more context. | L3: Review Queue
A4: Select Repo | B4: RepoA | D4: GitHub | E4: =IFERROR(IF(VLOOKUP($B$4,Data_RepoDetail!$A:$BZ,2,FALSE)="","Repo URL unavailable",HYPERLINK(VLOOKUP($B$4,Data_RepoDetail!$A:$BZ,2,FALSE),"Open Repo")),"Repo URL unavailable") | L4: Repo Detail
L5: Run Changes
A6: Repo | B6: =IFERROR(IF(VLOOKUP($B$4,Data_RepoDetail!$A:$BZ,1,FALSE)="","No repo selected.",VLOOKUP($B$4,Data_RepoDetail!$A:$BZ,1,FALSE)),"No repo selected.") | D6: Language | E6: =IFERROR(IF(VLOOKUP($B$4,Data_RepoDetail!$A:$BZ,3,FALSE)="","Unknown",VLOOKUP($B$4,Data_RepoDetail!$A:$BZ,3,FALSE)),"Unknown") | G6: Badges | H6: =IFERROR(IF(VLOOKUP($B$4,Data_RepoDetail!$A:$BZ,9,FALSE)="","None",VLOOKUP($B$4,Data_RepoDetail!$A:$BZ,9,FALSE)),"None") | L6: Executive Summary
A7: Overall Score | B7: =IFERROR(VLOOKUP($B$4,Data_RepoDetail!$A:$BZ,5,FALSE),"") | D7: Interest Score | E7: =IFERROR(VLOOKUP($B$4,Data_RepoDetail!$A:$BZ,6,FALSE),"") | G7: Flags | H7: =IFERROR(IF(VLOOKUP($B$4,Data_RepoDetail!$A:$BZ,10,FALSE)="","None",VLOOKUP($B$4,Data_RepoDetail!$A:$BZ,10,FALSE)),"None")
A8: Grade | B8: =IFERROR(IF(VLOOKUP($B$4,Data_RepoDetail!$A:$BZ,7,FALSE)="","—",VLOOKUP($B$4,Data_RepoDetail!$A:$BZ,7,FALSE)),"—") | D8: Tier | E8: =IFERROR(IF(VLOOKUP($B$4,Data_RepoDetail!$A:$BZ,8,FALSE)="","—",VLOOKUP($B$4,Data_RepoDetail!$A:$BZ,8,FALSE)),"—") | G8: Collections | H8: =IFERROR(IF(VLOOKUP($B$4,Data_RepoDetail!$A:$BZ,11,FALSE)="","—",VLOOKUP($B$4,Data_RepoDetail!$A:$BZ,11,FALSE)),"—")
A9: Security | B9: =IFERROR(IF(VLOOKUP($B$4,Data_RepoDetail!$A:$BZ,12,FALSE)="","unknown",VLOOKUP($B$4,Data_RepoDetail!$A:$BZ,12,FALSE)),"unknown") | D9: Security Score | E9: =IFERROR(VLOOKUP($B$4,Data_RepoDetail!$A:$BZ,13,FALSE),"") | G9: Trend | H9: =IFERROR(IF(VLOOKUP($B$4,Data_RepoDetail!$A:$BZ,18,FALSE)="","No trend history yet.",VLOOKUP($B$4,Data_RepoDetail!$A:$BZ,18,FALSE)),"No trend history yet.")
A11: Description | B11: =IFERROR(IF(VLOOKUP($B$4,Data_RepoDetail!$A:$BZ,4,FALSE)="","No description recorded yet.",VLOOKUP($B$4,Data_RepoDetail!$A:$BZ,4,FALSE)),"No description recorded yet.")
A13: Current State | E13: Why This Repo Looks This Way
A14: Ship Readiness | B14: =IFERROR(IF(VLOOKUP($B$4,Data_RepoDetail!$A:$BZ,14,FALSE)="","No summary recorded yet.",VLOOKUP($B$4,Data_RepoDetail!$A:$BZ,14,FALSE)),"No summary recorded yet.") | E14: Strongest Drivers | F14: =IFERROR(IF(VLOOKUP($B$4,Data_RepoDetail!$A:$BZ,19,FALSE)="","No briefing detail recorded yet.",VLOOKUP($B$4,Data_RepoDetail!$A:$BZ,19,FALSE)),"No briefing detail recorded yet.")
A15: Momentum | B15: =IFERROR(IF(VLOOKUP($B$4,Data_RepoDetail!$A:$BZ,15,FALSE)="","No summary recorded yet.",VLOOKUP($B$4,Data_RepoDetail!$A:$BZ,15,FALSE)),"No summary recorded yet.") | E15: Biggest Drags | F15: =IFERROR(IF(VLOOKUP($B$4,Data_RepoDetail!$A:$BZ,20,FALSE)="","No briefing detail recorded yet.",VLOOKUP($B$4,Data_RepoDetail!$A:$BZ,20,FALSE)),"No briefing detail recorded yet.")
A16: Security | B16: =IFERROR(IF(VLOOKUP($B$4,Data_RepoDetail!$A:$BZ,16,FALSE)="","No summary recorded yet.",VLOOKUP($B$4,Data_RepoDetail!$A:$BZ,16,FALSE)),"No summary recorded yet.") | E16: Last Movement | F16: =IFERROR(IF(VLOOKUP($B$4,Data_RepoDetail!$A:$BZ,30,FALSE)="","No briefing detail recorded yet.",VLOOKUP($B$4,Data_RepoDetail!$A:$BZ,30,FALSE)),"No briefing detail recorded yet.")
A17: Portfolio Fit | B17: =IFERROR(IF(VLOOKUP($B$4,Data_RepoDetail!$A:$BZ,17,FALSE)="","No summary recorded yet.",VLOOKUP($B$4,Data_RepoDetail!$A:$BZ,17,FALSE)),"No summary recorded yet.") | E17: Next Tier Gap | F17: =IFERROR(IF(VLOOKUP($B$4,Data_RepoDetail!$A:$BZ,21,FALSE)="","No briefing detail recorded yet.",VLOOKUP($B$4,Data_RepoDetail!$A:$BZ,21,FALSE)),"No briefing detail recorded yet.")
E18: Next Best Action | F18: =IFERROR(IF(VLOOKUP($B$4,Data_RepoDetail!$A:$BZ,22,FALSE)="","No briefing detail recorded yet.",VLOOKUP($B$4,Data_RepoDetail!$A:$BZ,22,FALSE)),"No briefing detail recorded yet.")
E19: Why This Action | F19: =IFERROR(IF(VLOOKUP($B$4,Data_RepoDetail!$A:$BZ,23,FALSE)="","No briefing detail recorded yet.",VLOOKUP($B$4,Data_RepoDetail!$A:$BZ,23,FALSE)),"No briefing detail recorded yet.")
A20: Dimension Breakdown | F20: What Changed
A21: Rank | B21: Dimension | C21: Score | D21: Summary | F21: Hotspot 1 | G21: =IFERROR(IF(VLOOKUP($B$4,Data_RepoDetail!$A:$BZ,24,FALSE)="","No hotspot recorded yet.",VLOOKUP($B$4,Data_RepoDetail!$A:$BZ,24,FALSE)),"No hotspot recorded yet.")
A22: 1 | B22: =IFERROR(VLOOKUP($B$4&"::1",Data_RepoDimensionRollups!$A:$F,4,FALSE),"") | C22: =IFERROR(VLOOKUP($B$4&"::1",Data_RepoDimensionRollups!$A:$F,5,FALSE),"") | D22: =IFERROR(VLOOKUP($B$4&"::1",Data_RepoDimensionRollups!$A:$F,6,FALSE),"") | F22: Hotspot 2 | G22: =IFERROR(IF(VLOOKUP($B$4,Data_RepoDetail!$A:$BZ,25,FALSE)="","No hotspot recorded yet.",VLOOKUP($B$4,Data_RepoDetail!$A:$BZ,25,FALSE)),"No hotspot recorded yet.")
A23: 2 | B23: =IFERROR(VLOOKUP($B$4&"::2",Data_RepoDimensionRollups!$A:$F,4,FALSE),"") | C23: =IFERROR(VLOOKUP($B$4&"::2",Data_RepoDimensionRollups!$A:$F,5,FALSE),"") | D23: =IFERROR(VLOOKUP($B$4&"::2",Data_RepoDimensionRollups!$A:$F,6,FALSE),"") | F23: Hotspot 3 | G23: =IFERROR(IF(VLOOKUP($B$4,Data_RepoDetail!$A:$BZ,26,FALSE)="","No hotspot recorded yet.",VLOOKUP($B$4,Data_RepoDetail!$A:$BZ,26,FALSE)),"No hotspot recorded yet.")
A24: 3 | B24: =IFERROR(VLOOKUP($B$4&"::3",Data_RepoDimensionRollups!$A:$F,4,FALSE),"") | C24: =IFERROR(VLOOKUP($B$4&"::3",Data_RepoDimensionRollups!$A:$F,5,FALSE),"") | D24: =IFERROR(VLOOKUP($B$4&"::3",Data_RepoDimensionRollups!$A:$F,6,FALSE),"")
A25: 4 | B25: =IFERROR(VLOOKUP($B$4&"::4",Data_RepoDimensionRollups!$A:$F,4,FALSE),"") | C25: =IFERROR(VLOOKUP($B$4&"::4",Data_RepoDimensionRollups!$A:$F,5,FALSE),"") | D25: =IFERROR(VLOOKUP($B$4&"::4",Data_RepoDimensionRollups!$A:$F,6,FALSE),"") | F25: What To Do Next
A26: 5 | B26: =IFERROR(VLOOKUP($B$4&"::5",Data_RepoDimensionRollups!$A:$F,4,FALSE),"") | C26: =IFERROR(VLOOKUP($B$4&"::5",Data_RepoDimensionRollups!$A:$F,5,FALSE),"") | D26: =IFERROR(VLOOKUP($B$4&"::5",Data_RepoDimensionRollups!$A:$F,6,FALSE),"") | F26: Recommended Action | G26: =IFERROR(IF(VLOOKUP($B$4,Data_RepoDetail!$A:$BZ,22,FALSE)="","No clear next action is recorded yet.",VLOOKUP($B$4,Data_RepoDetail!$A:$BZ,22,FALSE)),"No clear next action is recorded yet.")
A27: 6 | B27: =IFERROR(VLOOKUP($B$4&"::6",Data_RepoDimensionRollups!$A:$F,4,FALSE),"") | C27: =IFERROR(VLOOKUP($B$4&"::6",Data_RepoDimensionRollups!$A:$F,5,FALSE),"") | D27: =IFERROR(VLOOKUP($B$4&"::6",Data_RepoDimensionRollups!$A:$F,6,FALSE),"") | F27: Why This Action | G27: =IFERROR(IF(VLOOKUP($B$4,Data_RepoDetail!$A:$BZ,23,FALSE)="","No action rationale is recorded yet.",VLOOKUP($B$4,Data_RepoDetail!$A:$BZ,23,FALSE)),"No action rationale is recorded yet.")
A28: Where To Start | F28: Follow-Through Status | G28: =IFERROR(IF(VLOOKUP($B$4,Data_RepoDetail!$A:$BZ,32,FALSE)="","Unknown",VLOOKUP($B$4,Data_RepoDetail!$A:$BZ,32,FALSE)),"Unknown")
A29: Summary | B29: =IFERROR(IF(VLOOKUP($B$4,Data_RepoDetail!$A:$BZ,66,FALSE)="","No meaningful implementation hotspot is currently surfaced.",VLOOKUP($B$4,Data_RepoDetail!$A:$BZ,66,FALSE)),"No meaningful implementation hotspot is currently surfaced.") | F29: Follow-Through Summary | G29: =IFERROR(IF(VLOOKUP($B$4,Data_RepoDetail!$A:$BZ,33,FALSE)="","No follow-through evidence is recorded yet.",VLOOKUP($B$4,Data_RepoDetail!$A:$BZ,33,FALSE)),"No follow-through evidence is recorded yet.")
A30: Implementation Hotspot 1 | B30: =IFERROR(IF(VLOOKUP($B$4,Data_RepoDetail!$A:$BZ,67,FALSE)="","No implementation hotspot is currently surfaced.",VLOOKUP($B$4,Data_RepoDetail!$A:$BZ,67,FALSE)),"No implementation hotspot is currently surfaced.") | F30: Checkpoint Timing | G30: =IFERROR(IF(VLOOKUP($B$4,Data_RepoDetail!$A:$BZ,34,FALSE)="","Unknown",VLOOKUP($B$4,Data_RepoDetail!$A:$BZ,34,FALSE)),"Unknown")
A31: Implementation Hotspot 2 | B31: =IFERROR(IF(VLOOKUP($B$4,Data_RepoDetail!$A:$BZ,68,FALSE)="","No second implementation hotspot is currently surfaced.",VLOOKUP($B$4,Data_RepoDetail!$A:$BZ,68,FALSE)),"No second implementation hotspot is currently surfaced.") | F31: Escalation | G31: =IFERROR(IF(VLOOKUP($B$4,Data_RepoDetail!$A:$BZ,35,FALSE)="","Unknown",VLOOKUP($B$4,Data_RepoDetail!$A:$BZ,35,FALSE)),"Unknown")
A32: Implementation Hotspot 3 | B32: =IFERROR(IF(VLOOKUP($B$4,Data_RepoDetail!$A:$BZ,69,FALSE)="","No third implementation hotspot is currently surfaced.",VLOOKUP($B$4,Data_RepoDetail!$A:$BZ,69,FALSE)),"No third implementation hotspot is currently surfaced.") | F32: Escalation Summary | G32: =IFERROR(IF(VLOOKUP($B$4,Data_RepoDetail!$A:$BZ,36,FALSE)="","No stronger follow-through escalation is currently surfaced.",VLOOKUP($B$4,Data_RepoDetail!$A:$BZ,36,FALSE)),"No stronger follow-through escalation is currently surfaced.")
F33: Recovery / Retirement | G33: =IFERROR(IF(VLOOKUP($B$4,Data_RepoDetail!$A:$BZ,37,FALSE)="","None",VLOOKUP($B$4,Data_RepoDetail!$A:$BZ,37,FALSE)),"None")
A34: Arc F Signals | F34: Recovery Summary | G34: =IFERROR(IF(VLOOKUP($B$4,Data_RepoDetail!$A:$BZ,38,FALSE)="","No follow-through recovery or escalation-retirement signal is currently surfaced.",VLOOKUP($B$4,Data_RepoDetail!$A:$BZ,38,FALSE)),"No follow-through recovery or escalation-retirement signal is currently surfaced.")
A35: README Stale | B35: =IFERROR(VLOOKUP($B$4,Data_RepoDetail!$A:$BZ,71,FALSE),"—") | F35: Recovery Persistence | G35: =IFERROR(IF(VLOOKUP($B$4,Data_RepoDetail!$A:$BZ,39,FALSE)="","None",VLOOKUP($B$4,Data_RepoDetail!$A:$BZ,39,FALSE)),"None")
A36: Staleness Ratio | B36: =IFERROR(VLOOKUP($B$4,Data_RepoDetail!$A:$BZ,72,FALSE),"—") | F36: Recovery Persistence Summary | G36: =IFERROR(IF(VLOOKUP($B$4,Data_RepoDetail!$A:$BZ,40,FALSE)="","No follow-through recovery persistence signal is currently surfaced.",VLOOKUP($B$4,Data_RepoDetail!$A:$BZ,40,FALSE)),"No follow-through recovery persistence signal is currently surfaced.")
A37: README Last Touched (days) | B37: =IFERROR(VLOOKUP($B$4,Data_RepoDetail!$A:$BZ,73,FALSE),"—") | F37: Relapse Churn | G37: =IFERROR(IF(VLOOKUP($B$4,Data_RepoDetail!$A:$BZ,41,FALSE)="","None",VLOOKUP($B$4,Data_RepoDetail!$A:$BZ,41,FALSE)),"None")
A38: Code Last Touched (days) | B38: =IFERROR(VLOOKUP($B$4,Data_RepoDetail!$A:$BZ,74,FALSE),"—") | F38: Relapse Churn Summary | G38: =IFERROR(IF(VLOOKUP($B$4,Data_RepoDetail!$A:$BZ,42,FALSE)="","No relapse churn is currently surfaced.",VLOOKUP($B$4,Data_RepoDetail!$A:$BZ,42,FALSE)),"No relapse churn is currently surfaced.")
A39: Has Any Release | B39: =IFERROR(VLOOKUP($B$4,Data_RepoDetail!$A:$BZ,75,FALSE),"No") | F39: Recovery Freshness | G39: =IFERROR(IF(VLOOKUP($B$4,Data_RepoDetail!$A:$BZ,43,FALSE)="","None",VLOOKUP($B$4,Data_RepoDetail!$A:$BZ,43,FALSE)),"None")
A40: Latest Release Age (days) | B40: =IFERROR(VLOOKUP($B$4,Data_RepoDetail!$A:$BZ,76,FALSE),"—") | F40: Recovery Freshness Summary | G40: =IFERROR(IF(VLOOKUP($B$4,Data_RepoDetail!$A:$BZ,44,FALSE)="","No follow-through recovery freshness signal is currently surfaced.",VLOOKUP($B$4,Data_RepoDetail!$A:$BZ,44,FALSE)),"No follow-through recovery freshness signal is currently surfaced.")
A41: OSSF Score | B41: =IFERROR(VLOOKUP($B$4,Data_RepoDetail!$A:$BZ,77,FALSE),"—") | F41: Recovery Memory Reset | G41: =IFERROR(IF(VLOOKUP($B$4,Data_RepoDetail!$A:$BZ,45,FALSE)="","None",VLOOKUP($B$4,Data_RepoDetail!$A:$BZ,45,FALSE)),"None")
A42: OSSF Top Failing Checks | B42: =IFERROR(VLOOKUP($B$4,Data_RepoDetail!$A:$BZ,78,FALSE),"—") | F42: Recovery Memory Reset Summary | G42: =IFERROR(IF(VLOOKUP($B$4,Data_RepoDetail!$A:$BZ,46,FALSE)="","No follow-through recovery memory reset signal is currently surfaced.",VLOOKUP($B$4,Data_RepoDetail!$A:$BZ,46,FALSE)),"No follow-through recovery memory reset signal is currently surfaced.")
A43: Risk Posture | F43: Recovery Rebuild Strength | G43: =IFERROR(IF(VLOOKUP($B$4,Data_RepoDetail!$A:$BZ,47,FALSE)="","None",VLOOKUP($B$4,Data_RepoDetail!$A:$BZ,47,FALSE)),"None")
A44: Risk Tier | B44: =IFERROR(VLOOKUP($B$4,Data_RepoDetail!$A:$BZ,79,FALSE),"—") | F44: Recovery Rebuild Strength Summary | G44: =IFERROR(IF(VLOOKUP($B$4,Data_RepoDetail!$A:$BZ,48,FALSE)="","No follow-through recovery rebuild-strength signal is currently surfaced.",VLOOKUP($B$4,Data_RepoDetail!$A:$BZ,48,FALSE)),"No follow-through recovery rebuild-strength signal is currently surfaced.")
F45: Recovery Reacquisition | G45: =IFERROR(IF(VLOOKUP($B$4,Data_RepoDetail!$A:$BZ,49,FALSE)="","None",VLOOKUP($B$4,Data_RepoDetail!$A:$BZ,49,FALSE)),"None")
F46: Recovery Reacquisition Summary | G46: =IFERROR(IF(VLOOKUP($B$4,Data_RepoDetail!$A:$BZ,50,FALSE)="","No follow-through recovery reacquisition signal is currently surfaced.",VLOOKUP($B$4,Data_RepoDetail!$A:$BZ,50,FALSE)),"No follow-through recovery reacquisition signal is currently surfaced.")
F47: Reacquisition Durability | G47: =IFERROR(IF(VLOOKUP($B$4,Data_RepoDetail!$A:$BZ,51,FALSE)="","None",VLOOKUP($B$4,Data_RepoDetail!$A:$BZ,51,FALSE)),"None")
F48: Reacquisition Durability Summary | G48: =IFERROR(IF(VLOOKUP($B$4,Data_RepoDetail!$A:$BZ,52,FALSE)="","No follow-through reacquisition durability signal is currently surfaced.",VLOOKUP($B$4,Data_RepoDetail!$A:$BZ,52,FALSE)),"No follow-through reacquisition durability signal is currently surfaced.")
F49: Reacquisition Confidence | G49: =IFERROR(IF(VLOOKUP($B$4,Data_RepoDetail!$A:$BZ,53,FALSE)="","None",VLOOKUP($B$4,Data_RepoDetail!$A:$BZ,53,FALSE)),"None")
F50: Reacquisition Confidence Summary | G50: =IFERROR(IF(VLOOKUP($B$4,Data_RepoDetail!$A:$BZ,54,FALSE)="","No follow-through reacquisition confidence-consolidation signal is currently surfaced.",VLOOKUP($B$4,Data_RepoDetail!$A:$BZ,54,FALSE)),"No follow-through reacquisition confidence-consolidation signal is currently surfaced.")
F51: Reacquisition Softening Decay | G51: =IFERROR(IF(VLOOKUP($B$4,Data_RepoDetail!$A:$BZ,55,FALSE)="","None",VLOOKUP($B$4,Data_RepoDetail!$A:$BZ,55,FALSE)),"None")
F52: Reacquisition Softening Decay Summary | G52: =IFERROR(IF(VLOOKUP($B$4,Data_RepoDetail!$A:$BZ,56,FALSE)="","No reacquisition softening-decay signal is currently surfaced.",VLOOKUP($B$4,Data_RepoDetail!$A:$BZ,56,FALSE)),"No reacquisition softening-decay signal is currently surfaced.")
F53: Reacquisition Confidence Retirement | G53: =IFERROR(IF(VLOOKUP($B$4,Data_RepoDetail!$A:$BZ,57,FALSE)="","None",VLOOKUP($B$4,Data_RepoDetail!$A:$BZ,57,FALSE)),"None")
F54: Reacquisition Confidence Retirement Summary | G54: =IFERROR(IF(VLOOKUP($B$4,Data_RepoDetail!$A:$BZ,58,FALSE)="","No reacquisition confidence-retirement signal is currently surfaced.",VLOOKUP($B$4,Data_RepoDetail!$A:$BZ,58,FALSE)),"No reacquisition confidence-retirement signal is currently surfaced.")
F55: Revalidation Recovery | G55: =IFERROR(IF(VLOOKUP($B$4,Data_RepoDetail!$A:$BZ,59,FALSE)="","None",VLOOKUP($B$4,Data_RepoDetail!$A:$BZ,59,FALSE)),"None")
F56: Revalidation Recovery Summary | G56: =IFERROR(IF(VLOOKUP($B$4,Data_RepoDetail!$A:$BZ,60,FALSE)="","No post-revalidation recovery or confidence re-earning signal is currently surfaced.",VLOOKUP($B$4,Data_RepoDetail!$A:$BZ,60,FALSE)),"No post-revalidation recovery or confidence re-earning signal is currently surfaced.")
F57: Progress Checkpoint | G57: =IFERROR(IF(VLOOKUP($B$4,Data_RepoDetail!$A:$BZ,61,FALSE)="","Use the next run or linked artifact to confirm whether the recommendation moved.",VLOOKUP($B$4,Data_RepoDetail!$A:$BZ,61,FALSE)),"Use the next run or linked artifact to confirm whether the recommendation moved.")
F58: Portfolio Catalog | G58: =IFERROR(IF(VLOOKUP($B$4,Data_RepoDetail!$A:$BZ,62,FALSE)="","No portfolio catalog contract is recorded yet.",VLOOKUP($B$4,Data_RepoDetail!$A:$BZ,62,FALSE)),"No portfolio catalog contract is recorded yet.")
F59: Operating Path | G59: =IFERROR(IF(VLOOKUP($B$4,Data_RepoDetail!$A:$BZ,66,FALSE)="","Operating Path: Unspecified (legacy confidence) — No operating-path rationale is recorded yet.",VLOOKUP($B$4,Data_RepoDetail!$A:$BZ,66,FALSE)),"Operating Path: Unspecified (legacy confidence) — No operating-path rationale is recorded yet.")
F60: Intent Alignment | G60: =IFERROR(IF(VLOOKUP($B$4,Data_RepoDetail!$A:$BZ,63,FALSE)="","missing-contract: Intent alignment cannot be judged until a portfolio catalog contract exists.",VLOOKUP($B$4,Data_RepoDetail!$A:$BZ,63,FALSE)),"missing-contract: Intent alignment cannot be judged until a portfolio catalog contract exists.")
F61: Scorecard | G61: =IFERROR(IF(VLOOKUP($B$4,Data_RepoDetail!$A:$BZ,64,FALSE)="","Scorecard: No maturity scorecard is recorded yet.",VLOOKUP($B$4,Data_RepoDetail!$A:$BZ,64,FALSE)),"Scorecard: No maturity scorecard is recorded yet.")
F62: Maturity Gap | G62: =IFERROR(IF(VLOOKUP($B$4,Data_RepoDetail!$A:$BZ,65,FALSE)="","No maturity gap summary is recorded yet.",VLOOKUP($B$4,Data_RepoDetail!$A:$BZ,65,FALSE)),"No maturity gap summary is recorded yet.")
F63: Action Candidate 2 | G63: =IFERROR(IF(VLOOKUP($B$4,Data_RepoDetail!$A:$BZ,28,FALSE)="","No second action candidate recorded yet.",VLOOKUP($B$4,Data_RepoDetail!$A:$BZ,28,FALSE)),"No second action candidate recorded yet.")
F64: Action Candidate 3 | G64: =IFERROR(IF(VLOOKUP($B$4,Data_RepoDetail!$A:$BZ,29,FALSE)="","No third action candidate recorded yet.",VLOOKUP($B$4,Data_RepoDetail!$A:$BZ,29,FALSE)),"No third action candidate recorded yet.")
A65: Use Score Explainer | B65: 'Score Explainer'!A1 | D65: Go To Explorer | E65: 'Portfolio Explorer'!A1 | F65: Go To Queue | G65: 'Review Queue'!A1

Sheet Executive Summary
A1: Executive Summary | N1: Quick Links
A2: Profile: default | Collection: all | N2: Dashboard
A3: Use the left side for the short leadership story and the right side for operator evidence you may need to defend the next move. | N3: Review Queue
A4: Leadership Brief | N4: Repo Detail
A5: Portfolio Health | B5: 1 repos are shipped, the portfolio average is 0.65, and RepoA set the current high-water mark. | N5: Run Changes
A6: Top Attention | B6: RepoC still needs security follow-through before the queue will calm down. Critical security pressure is concentrated in 1 repos. | N6: Executive Summary
A7: Run Changes | B7: Average score moved +0.020; 0 meaningful improvements, 0 regressions, 1 promotions, and 1 demotions were recorded.
A8: Queue Pressure | B8: 1 blocked, 1 urgent, 1 ready, and 1 deferred item(s) are currently in the queue.
A9: What Changed | B9: RepoC drift needs review and RepoB reopened a release checklist item.
A10: Portfolio Grade | C10: Avg Score | E10: Critical Repos | G10: Improving | I10: Regressing
A11: B | C11: 0.65 | E11: 1 | G11: 0 | I11: 0
A12: Follow-Through Hotspot | B12: No outstanding follow-through hotspot
A13: Escalation Hotspot | B13: No outstanding follow-through hotspot
A14: Top Profile Leaders | B14: No active recovery or retirement hotspot | E14: Top Movers | I14: Top 5 Attention Items
A15: Repo | B15: Profile Score | C15: Tier | E15: Repo | F15: Delta | G15: Tier Change | I15: Repo | J15: Counts | K15: Why Now | L15: Next Step
A16: RepoA | B16: 0.88 | C16: shipped | E16: RepoA | F16: 0.09 | G16: functional -> shipped | I16: RepoC | J16: B1/U0/R0 | K16: Security drift needs review | L16: Open the governed control preview and decide whether to apply CodeQL.
A17: RepoB | B17: 0.62 | C17: functional | E17: RepoC | F17: -0.08 | G17: functional -> wip | I17: RepoB | J17: B0/U1/R0 | K17: Release checklist reopened | L17: Re-run the release checklist and close the missing item.
A18: RepoC | B18: 0.44 | C18: wip | I18: RepoA | J18: B0/U0/R1 | K18: Archive old brainstorm notes | L18: Leave this alone unless priorities change.
A19: Rebuild Hotspot | B19: No rebuilding recovery-memory hotspot
A20: Rebuild Strength Hotspot | B20: No rebuilding-after-reset hotspot
A21: Reacquiring Hotspot | B21: No near-reacquisition hotspot
A22: Scenario Preview | B22: No re-acquired hotspot | D22: Operator Control Center
A23: Projected Avg Score Delta | B23: 0 | D23: Headline | E23: RepoC still needs security follow-through before the queue will calm down.
A24: Projected Promotions | B24: 0 | D24: Queue Counts | E24: 1 blocked, 1 urgent, 1 ready, 1 deferred
A25: Holding Reacquired Hotspot | B25: No holding re-acquisition hotspot | D25: Source Run | E25: sample-user:2026-04-12T12:00:00+00:00
A26: Durable Reacquired Hotspot | B26: No durable re-acquisition hotspot | D26: Next Run | E26: incremental via adaptive
A27: Softening Reacquired Hotspot | B27: No softening re-acquisition hotspot | D27: Watch Decision | E27: The current baseline is still compatible, so incremental watch remains safe for the next run.
A28: Fragile Reacquisition Confidence Hotspot | B28: No fragile re-acquisition confidence hotspot | D28: What To Do Next | E28: Review RepoC first, then close RepoB's reopened checklist item.
A29: Reacquisition Softening Hotspot | B29: No reacquisition softening hotspot | D29: Trend | E29: Stable — Queue pressure is stable but still sticky.
A30: Revalidation Needed Hotspot | B30: No reacquisition revalidation hotspot | D30: Primary Target | E30: No active target
A31: Retired Confidence Hotspot | B31: No retired re-acquisition confidence hotspot | D31: Resolution Counts | E31: New 0 | Resolved 0 | Persisting 0
A32: Under Revalidation Hotspot | B32: No under-revalidation recovery hotspot | D32: Why Top Target | E32: RepoC remains the top target because live drift is still open.
A33: Rebuilding Restored Confidence Hotspot | B33: No rebuilding restored-confidence hotspot | D33: Closure Guidance | E33: Clear RepoC's security drift before moving to lower-pressure work.
A34: Re-Earning Confidence Hotspot | B34: No confidence re-earning hotspot | D34: Aging Pressure | E34: Chronic 0 | Newly stale 0 | Longest No persisting item
A35: Just Re-Earned Confidence Hotspot | B35: No just re-earned confidence hotspot | D35: What We Tried | E35: No recent intervention recorded
A36: Holding Re-Earned Confidence Hotspot | B36: No holding re-earned confidence hotspot | D36: Last Outcome | E36: No Change
... A88: Reacquisition Durability | B88: No follow-through reacquisition durability signal is currently surfaced. | D88: Calibration Snapshot | E88: High-confidence hit rate 0% | 0 reopened
A89: Reacquisition Confidence | B89: No follow-through reacquisition confidence-consolidation signal is currently surfaced.
A90: Operator Focus | B90: Act Now
A91: Focus Summary | B91: 2 item(s) need immediate action first, led by RepoC, RepoB.
A92: Focus Line | B92: Act Now: Governed security drift is still unresolved.
A93: Trust Summary | B93: verify-first — The recommendation is sound, but recent reopen noise means it should still be reviewed before acting.
A94: Biggest Opportunity | B94: RepoA
A95: Focus This Week | B95: Review RepoC first, then close RepoB's reopened checklist item.

Sheet By Lens
A1: By Lens | K1: Quick Links
A2: Compare the same repos through different decision lenses so you can separate shipped work, risk, momentum, and showcase value. | K2: Dashboard
A3: Current view: profile default | collection all | use this sheet to compare the same repo through multiple decision lenses. | K3: Review Queue
K4: Repo Detail
A5: Repo | B5: Profile Score | C5: Tier | D5: Ship Readiness | E5: Maintenance Risk | F5: Showcase | G5: Security | H5: Momentum | I5: Portfolio Fit | K5: Run Changes
A6: RepoA | B6: 0.88 | C6: shipped | D6: 0.89 | E6: 0 | F6: 0 | G6: 0.82 | H6: 0.75 | I6: 0.86 | K6: Executive Summary
A7: RepoB | B7: 0.62 | C7: functional | D7: 0.63 | E7: 0 | F7: 0 | G7: 0.66 | H7: 0.54 | I7: 0.58
A8: RepoC | B8: 0.44 | C8: wip | D8: 0.42 | E8: 0 | F8: 0 | G8: 0.28 | H8: 0.31 | I8: 0.36

Sheet By Collection
A1: By Collection | J1: Quick Links
A2: Use this sheet to understand which collections are concentrated, which repos lead them, and where your showcase value is clustered. | J2: Dashboard
A3: Current profile: default. Use this sheet to see how each collection groups related repos and where its best work sits. | J3: Review Queue
J4: Repo Detail
A5: Collection | B5: Repos | C5: Description | D5: Top Repo | E5: Top Score | J5: Run Changes
A6: showcase | B6: 1 | C6: Best examples to show other people. | D6: RepoA | E6: 0.88 | J6: Executive Summary

Sheet Trend Summary
A1: Trend Summary | J1: Quick Links
A2: Track portfolio movement over time, then scan the short repo trendlines below to see who is actually improving or drifting. | J2: Dashboard
A3: Use this sheet when you want portfolio-wide movement first, then repo-level trendlines second. | J3: Review Queue
J4: Repo Detail
A5: Date | B5: Average Score | C5: Repos | D5: Shipped | E5: Functional | F5: Review Emitted | G5: Campaign Drift | H5: Governance Drift | J5: Run Changes
A6: 2026-04-12 | B6: 0.65 | C6: 3 | D6: 1 | E6: 1 | F6: yes | G6: 1 | H6: 1 | J6: Executive Summary
A9: Top Repo Trendlines
A10: Repo | B10: Trendline | C10: Latest Score
A11: RepoA | C11: 0.88
A12: RepoB | C12: 0.62
A13: RepoC | C13: 0.44

Sheet Run Changes
A1: Run Changes | N1: Quick Links
A2: Use this sheet to answer one question quickly: what moved since the last run, and what actually needs follow-through now? | N2: Dashboard
A3: Average score moved +0.020; 0 meaningful improvements, 0 regressions, 1 promotions, and 1 demotions were recorded. | N3: Review Queue
A4: Read this page top to bottom: scan the summary cards first, then check regressions, blocked items, and new security or governance pressure. | N4: Repo Detail
A5: Comparison Window | B5: 2026-04-05 -> 2026-04-12 | N5: Run Changes
A6: Improvements | C6: Regressions | E6: Promotions | G6: Demotions | I6: Security | K6: Governance | N6: Executive Summary
A7: 0 | C7: 0 | E7: 1 | G7: 1 | I7: 1 | K7: 1
A9: Biggest Score Gains
A10: Repo | B10: Delta | C10: New Score
A11: RepoA | B11: 0.09 | C11: 0.88
A12: RepoB | B12: -0.06 | C12: 0.62
A13: RepoC | B13: -0.08 | C13: 0.44
A15: Biggest Regressions
A16: Repo | B16: Delta | C16: New Score
A17: RepoC | B17: -0.08 | C17: 0.44
A18: RepoB | B18: -0.06 | C18: 0.62
A19: RepoA | B19: 0.09 | C19: 0.88
A21: Tier Promotions / Demotions
A22: Repo | B22: Old Tier | C22: New Tier | D22: Movement
A23: RepoA | B23: functional | C23: shipped | D23: promotion
A24: RepoC | B24: functional | C24: wip | D24: demotion
A26: Newly Blocked Items
A27: Repo | B27: Item | C27: Why
A28: RepoC | B28: Security drift needs review | C28: Governed security drift is still unresolved.
A30: Reopened Items
A31: Repo | B31: Title | C31: Type
A32: RepoB | B32: Release checklist reopened | C32: reopened-review
A34: New Security / Governance Pressure
A35: Repo | B35: Signal | C35: Area
A36: sample-user/RepoC | B36: already-enabled | C36: governance
A37: RepoC | B37: critical | C37: security

Sheet Campaigns
A1: Campaigns | M1: Quick Links
A2: Managed campaign state stays local-authoritative here. This sheet is where you see open work, stale items, and whether there is anything to reconcile. | M2: Dashboard
M3: Review Queue
A4: Current Campaign State | J4: Action Sync Readiness | M4: Repo Detail
A5: Campaign | B5: Security Review | J5: Action Sync Readiness | K5: No current campaign needs Action Sync yet, so the safest next move is to keep the story local. | M5: Run Changes
A6: Request State | B6: Campaign requested from the current report facts. | J6: Next Action Sync Step | K6: Stay local for now; no current campaign needs preview or apply. | M6: Executive Summary
A7: Row State | B7: Campaign rows are present. External mutation stays manual until writeback apply is explicitly requested. | J7: Apply Packet | K7: No current campaign has a safe execution handoff yet, so the local story should stay local for now.
A8: Profile | B8: default | J8: Command Hint | K8: No Action Sync command is recommended yet.
A9: Collection | B9: all | J9: Post-Apply Monitoring | K9: No recent Action Sync apply needs post-apply monitoring yet, so the local weekly story can stay local.
A10: Actions | B10: 1 | J10: Next Monitoring Step | K10: Stay local for now; no recent Action Sync apply needs post-apply follow-up yet.
A11: Repos | B11: 1 | J11: Campaign Tuning | K11: Campaign tuning is neutral because there is not enough outcome history yet to bias tied recommendations.
A12: Sync Mode | B12: reconcile | J12: Next Tie-Break Candidate | K12: No current campaign needs a tuning tie-break yet.
A13: GitHub Projects | B13: disabled | J13: Historical Portfolio Intelligence | K13: Historical portfolio intelligence is still thin, so the weekly story should stay grounded in the current run and recent operator queue.
J14: Next Historical Focus | K14: Stay local for now; no repo has enough cross-run intervention evidence to demand a historical follow-up read yet.
A15: Repo | B15: Issue | C15: Topics | D15: Projects | E15: Notion Actions | F15: Action IDs | G15: Drift | H15: Sync Mode | J15: Automation Guidance | K15: Automation guidance stays quiet until a campaign has a clearly safe preview, follow-up, or manual-only posture.
A16: RepoC | B16: [Repo Auditor] Security Review | C16: ghra-call-security-review | D16: 0 | E16: 1 | G16: no | H16: reconcile | J16: Next Safe Automation Step | K16: Stay local for now; no current campaign has a stronger safe automation posture than manual review.
J17: Approval Workflow | K17: No current approval needs review yet, so the approval workflow can stay local for now.
J18: Next Approval Review | K18: Stay local for now; no current approval needs review.

Sheet Governance Controls
A1: Governance Controls | J1: Quick Links
A2: This sheet shows the current governed control family only: readiness, drift, re-approval need, and rollback visibility. | J2: Dashboard
J3: Review Queue
A4: Governance Snapshot | J4: Repo Detail
A5: Status | B5: Drifted | J5: Run Changes
A6: Selected View | B6: all | J6: Executive Summary
A7: Approval | B7: Preview only
A8: Needs Re-Approval | B8: no
A9: Rollback Available | B9: 1
A10: Headline | B10: Governed security drift needs review.
A11: Repo | B11: Action | C11: State | D11: Expected Lift | E11: Effort | F11: Source | G11: Why
A12: RepoC | B12: Enable CodeQL default setup | C12: Ready | D12: 0.12 | F12: github

Sheet Print Pack
A1: Print Pack | J1: Quick Links
A2: Profile: default | Collection: all | J2: Dashboard
J3: Review Queue
A4: Page 1: Leadership Brief | D4: Workflow Guidance | J4: Repo Detail
A5: Portfolio Grade | B5: B | D5: Product Mode | E5: Action Sync: use this artifact to confirm the local campaign story first, then preview or apply GitHub, GitHub Projects, or Notion mirrors only after the repo-level decision is settled. | J5: Run Changes
A6: Average Score | B6: 0.65 | D6: Artifact Role | E6: Local report remains authoritative; campaigns, writeback, and GitHub Projects are managed mirrors of the decision already made here. | J6: Executive Summary
A7: Portfolio Headline | B7: RepoC still needs security follow-through before the queue will calm down. | D7: Reading Order | E7: Read Review Queue first, then the control-center headline and primary target, then the campaign preview or writeback section before syncing outward.
A8: Queue Pressure | B8: 1 blocked, 1 urgent, 1 ready, and 1 deferred item(s) are currently in the queue. | D8: Next Best Step | E8: Keep the local artifact as the source of truth, then use campaign preview or writeback only when the repo decision is already clear.
A9: Run Changes | B9: Average score moved +0.020; 0 meaningful improvements, 0 regressions, 1 promotions, and 1 demotions were recorded. | D9: Action Sync Readiness | E9: No current campaign needs Action Sync yet, so the safest next move is to keep the story local.
A10: What To Do This Week | B10: Review RepoC first, then close RepoB's reopened checklist item. Start with RepoC if you need a concrete place to begin. | D10: Next Action Sync Step | E10: Stay local for now; no current campaign needs preview or apply.
A11: Trust / Actionability | B11: verify-first — The recommendation is sound, but recent reopen noise means it should still be reviewed before acting. | D11: Apply Packet | E11: No current campaign has a safe execution handoff yet, so the local story should stay local for now.
A12: Top Attention Items | B12: 4 | D12: Command Hint | E12: No Action Sync command is recommended yet.
A13: What Changed | B13: RepoC drift needs review and RepoB reopened a release checklist item. | D13: Post-Apply Monitoring | E13: No recent Action Sync apply needs post-apply monitoring yet, so the local weekly story can stay local.
A14: Why It Matters | B14: Live drift is still present, so security work should stay ahead of lower-pressure cleanup. | D14: Next Monitoring Step | E14: Stay local for now; no recent Action Sync apply needs post-apply follow-up yet.
A15: Decision This Week | B15: Review RepoC first, then close RepoB's reopened checklist item. | D15: Campaign Tuning | E15: Campaign tuning stays neutral until there is enough outcome history to bias tied recommendations.
A16: Follow-Through | B16: Act Now: Governed security drift is still unresolved. Next checkpoint: Use the next run or linked artifact to confirm whether the recommendation moved. | D16: Next Tie-Break Candidate | E16: No current campaign needs a tie-break candidate yet.
A17: Primary Target | B17: No active target | D17: Historical Portfolio Intelligence | E17: Historical portfolio intelligence is still thin, so the weekly story should stay grounded in the current run and recent operator queue.
A18: Why Top Target | B18: RepoC remains the top target because live drift is still open. | D18: Next Historical Focus | E18: Stay local for now; no repo has enough cross-run intervention evidence to demand a historical follow-up read yet.
A19: Recovery / Retirement | B19: No follow-through recovery or escalation-retirement signal is currently surfaced. | D19: Automation Guidance | E19: Automation guidance stays quiet until a campaign has a clearly safe preview, follow-up, or manual-only posture.
A20: Recovery Persistence | B20: No follow-through recovery persistence signal is currently surfaced. | D20: Next Safe Automation Step | E20: Stay local for now; no current campaign has a stronger safe automation posture than manual review.
A21: Relapse Churn | B21: No relapse churn is currently surfaced. | D21: Approval Workflow | E21: No current approval needs review yet, so the approval workflow can stay local for now.
A22: Recovery Freshness | B22: No follow-through recovery freshness signal is currently surfaced. | D22: Next Approval Review | E22: Stay local for now; no current approval needs review.
A23: Recovery Memory Reset | B23: No follow-through recovery memory reset signal is currently surfaced.
A24: Recovery Rebuild Strength | B24: No follow-through recovery rebuild-strength signal is currently surfaced.
A25: Recovery Reacquisition | B25: No follow-through recovery reacquisition signal is currently surfaced.
A26: Reacquisition Durability | B26: No follow-through reacquisition durability signal is currently surfaced.
A27: Reacquisition Confidence | B27: No follow-through reacquisition confidence-consolidation signal is currently surfaced.
A28: Operator Focus | B28: Act Now
A29: Focus Summary | B29: 2 item(s) need immediate action first, led by RepoC, RepoB.
A30: Focus Line | B30: Act Now: Governed security drift is still unresolved.
A31: What We Tried | B31: No recent intervention recorded
A32: Last Outcome | B32: No Change
A33: Resolution Evidence | B33: No resolution evidence is recorded yet.
A34: Recovery Counts | B34: Confirmed resolved 0 | Reopened 0
... A69: Calibration Snapshot | B69: High-confidence hit rate 0% | 0 reopened
A70: Top Attention | E70: Top Repo Drilldowns
A71: RepoC | B71: Act Now | C71: Governed security drift is still unresolved. | D71: Open the governed control preview and decide whether to apply CodeQL. | E71: RepoC | F71: Open the governed control preview and decide whether to apply CodeQL. No action rationale is recorded yet.
A72: RepoB | B72: Act Now | C72: A previously quiet repo reopened a visible checklist item. | D72: Re-run the release checklist and close the missing item. | E72: RepoB | F72: Re-run the release checklist and close the missing item. No action rationale is recorded yet.
A73: RepoA | B73: Watch Closely | C73: RepoA is healthy enough that a small polish task would keep it strong. | D73: Tidy the release notes and publish the next small maintenance release. | E73: RepoA | F73: Tidy the release notes and publish the next small maintenance release. No action rationale is recorded yet.
A74: RepoA | B74: Watch Closely | C74: This is cleanup-only work with no current pressure. | D74: Leave this alone unless priorities change.
A76: Page 2: Changes and Governance
A77: Top Material Change Families | D77: Governance Highlights
A78: Security Change | B78: 1 | D78: Status | E78: Drifted
A79: Reopened Review | B79: 1 | D79: Needs Re-Approval | E79: no
D80: Drift Count | E80: 1
D81: Rollback Available | E81: 1
A84: Compare Snapshot
A85: Average Score Delta | B85: 0.02
A86: Repo Changes | B86: 2

Sheet Action Items
A1: Action Items — 4 prioritized improvements
A7: All Actions (Prioritized)
A8: # | B8: Repo | C8: Action | D8: Impact | E8: Effort | F8: Dimension
A9: 1 | B9: RepoC | C9: Improve testing (currently 0.2) | D9: Close 0.110 gap to functional | E9: Med | F9: testing
A10: 2 | B10: RepoC | C10: Improve security (currently 0.2) | D10: Close 0.110 gap to functional | E10: Med | F10: security
A11: 3 | B11: RepoB | C11: Improve release (currently 0.5) | D11: Close 0.130 gap to shipped | E11: Med | F11: release
A12: 4 | B12: RepoB | C12: Improve testing (currently 0.6) | D12: Close 0.130 gap to shipped | E12: Med | F12: testing

Sheet Activity
A1: Repo | B1: Commit Pattern | C1: Days Since Push | D1: Total Commits | E1: Recent 3mo | F1: Bus Factor | G1: Release Count | H1: Activity Score | I1: Tier
A2: RepoA | B2: — | C2: — | D2: — | E2: — | F2: — | G2: — | H2: 0 | I2: shipped
A3: RepoB | B3: — | C3: — | D3: — | E3: — | F3: — | G3: — | H3: 0 | I3: functional
A4: RepoC | B4: — | C4: — | D4: — | E4: — | F4: — | G4: — | H4: 0 | I4: wip

Sheet All Repos
A1: Repo | B1: Grade | C1: Score | D1: Interest | E1: Interest Grade | F1: Interest Tier | G1: Tier | H1: Badges | I1: Next Badge | J1: Language | K1: Topics | L1: Commit Pattern | M1: Bus Factor | N1: Days Since Push | O1: Commits | P1: Releases | Q1: Has Release | R1: README Stale | S1: Test Files | T1: Test Framework | U1: LOC | V1: TODO Density | W1: PR Merge % | X1: Comment Ratio | Y1: Dep Count | Z1: Libyears | AA1: Stars | AB1: Private | AC1: Flags | AD1: Description | AE1: Biggest Drag | AF1: Why This Grade | AG1: Tech Novelty | AH1: Burst | AI1: Ambition | AJ1: Storytelling | AK1: Created | AL1: Size (KB) | AM1: Trend | AN1: Risk Tier | AP1: Quick Links
A2: RepoA | B2: A | C2: 0.88 | D2: 0.61 | E2: — | F2: — | G2: shipped | H2: fresh, tested | J2: Python | K2: python, cli | L2: — | M2: — | N2: — | O2: — | P2: — | Q2: No | R2: No | S2: 0 | T2: — | U2: 0 | V2: 0 | W2: 0 | X2: 0 | Y2: — | Z2: — | AA2: 12 | AB2: No | AD2: A polished shipped project. | AE2: documentation (0.8) | AF2: A: documentation=0.8, testing=0.9 | AG2: 0 | AH2: 0 | AI2: 0 | AJ2: 0 | AL2: 0 | AP2: Dashboard
A3: RepoB | B3: C | C3: 0.62 | D3: 0.37 | E3: — | F3: — | G3: functional | J3: TypeScript | K3: typescript, web | L3: — | M3: — | N3: — | O3: — | P3: — | Q3: No | R3: No | S3: 0 | T3: — | U3: 0 | V3: 0 | W3: 0 | X3: 0 | Y3: — | Z3: — | AA3: 5 | AB3: No | AC3: release-checklist-open | AD3: A functional project with follow-through left to do. | AE3: release (0.5) | AF3: C: release=0.5, testing=0.6 | AG3: 0 | AH3: 0 | AI3: 0 | AJ3: 0 | AL3: 0 | AP3: Review Queue
A4: RepoC | B4: D | C4: 0.44 | D4: 0.16 | E4: — | F4: — | G4: wip | J4: Python | K4: python, security | L4: — | M4: — | N4: — | O4: — | P4: — | Q4: No | R4: No | S4: 0 | T4: — | U4: 0 | V4: 0 | W4: 0 | X4: 0 | Y4: — | Z4: — | AA4: 1 | AB4: No | AC4: no-tests, security-review | AD4: A risky work-in-progress project. | AE4: testing (0.2) | AF4: D: testing=0.2, security=0.2 | AG4: 0 | AH4: 0 | AI4: 0 | AJ4: 0 | AL4: 0 | AP4: Repo Detail
A5: SUMMARY | C5: =AVERAGE(C2:C4) | D5: =AVERAGE(D2:D4) | AP5: Run Changes
AP6: Executive Summary

Sheet Badges
A1: Badge Dashboard
A2: Total badges earned: 2 across 3 repos
A4: Badge | B4: Repos Earned | C4: % of Portfolio
A5: fresh | B5: 1 | C5: 33%
A6: tested | B6: 1 | C6: 33%
A9: Achievement Board
A10: Repo | B10: Badges
A11: RepoA | B11: 2
A12: RepoB | B12: 0
A13: RepoC | B13: 0

Sheet Changes
A1: Changes Since Last Audit
A3: Promotions | B3: 1 | C3: Demotions | D3: 1 | E3: Avg Score Delta | F3: 0.02
A5: Tier Changes
A6: Repo | B6: Old Tier | C6: New Tier | D6: Old Score | E6: New Score | F6: Direction
A7: RepoA | B7: functional | C7: shipped | D7: 0.79 | E7: 0.88 | F7: promotion
A8: RepoC | B8: functional | C8: wip | D8: 0.52 | E8: 0.44 | F8: demotion
A10: Significant Score Changes
A11: Repo | B11: Old Score | C11: New Score | D11: Delta
A12: RepoA | B12: 0.79 | C12: 0.88 | D12: 0.09
A13: RepoB | B13: 0.68 | C13: 0.62 | D13: -0.06
A14: RepoC | B14: 0.52 | C14: 0.44 | D14: -0.08
A16: Material Changes
A17: Repo | B17: Type | C17: Severity | D17: Title
A18: RepoB | B18: reopened-review | C18: 0.51 | D18: Release checklist reopened
A19: RepoC | B19: security-change | C19: 0.84 | D19: Security posture needs attention

Sheet Compare
A1: Compare Summary
A2: Previous: 2026-04-05
A3: Current: 2026-04-12
A4: Average score delta: +0.020
A6: Lens | B6: Delta
A7: ship_readiness | B7: 0.03
A8: security_posture | B8: -0.01
A11: Repo | B11: Score Delta | C11: Tier Change | D11: Security | E11: Hotspots | F11: Collections
A12: RepoA | B12: 0.09 | C12: functional -> shipped | D12: watch -> healthy | E12: 2 -> 1 | F12: — -> showcase
A13: RepoC | B13: -0.08 | C13: functional -> wip | D13: watch -> critical | E13: 1 -> 1 | F13: — -> —

Sheet Data_ActionSyncAutomation
A1: Campaign Type | B1: Label | C1: Automation Posture | D1: Review Required | E1: Requires Approval | F1: Recommended Command | G1: Recommended Follow Up | H1: Summary

Sheet Data_ActionSyncOutcomes
A1: Campaign Type | B1: Label | C1: Latest Target | D1: Latest Run Mode | E1: Recent Apply Count | F1: Monitored Repo Count | G1: Monitoring State | H1: Pressure Effect | I1: Drift State | J1: Reopen State | K1: Rollback State | L1: Follow-Up Recommendation | M1: Top Repos | N1: Summary

Sheet Data_Actions
A1: Repo | B1: Key | C1: Title | D1: Lens | E1: Effort | F1: Confidence | G1: Expected Lens Delta | H1: Expected Tier Movement | I1: Rationale
A2: RepoA | C2: Publish the next maintenance release | F2: 0 | G2: 0
A3: RepoB | C3: Close the reopened release item | F3: 0 | G3: 0
A4: RepoC | C4: Preview governance controls | F4: 0 | G4: 0

Sheet Data_ApprovalLedger
A1: Approval ID | B1: Subject Type | C1: Subject Key | D1: Label | E1: Approval State | F1: Follow-Up State | G1: Source Run ID | H1: Fingerprint | I1: Approved At | J1: Approved By | K1: Last Reviewed At | L1: Last Reviewed By | M1: Follow-Up Cadence Days | N1: Next Follow-Up Due At | O1: Stale Approval | P1: Approval Ready | Q1: Apply Ready After Approval | R1: Approval Command | S1: Follow-Up Command | T1: Manual Apply Command | U1: Summary

Sheet Data_CampaignTuning
A1: Campaign Type | B1: Label | C1: Tuning Status | D1: Recommendation Bias | E1: Judged Count | F1: Monitor Now Count | G1: Holding Clean Rate | H1: Drift Return Rate | I1: Reopen Rate | J1: Rollback Watch Rate | K1: Pressure Reduction Rate | L1: Summary

Sheet Data_Campaigns
A1: Campaign Type | B1: Label | C1: Profile | D1: Collection | E1: Actions | F1: Repos
A2: security-review | B2: Security Review | C2: default | E2: 1 | F2: 1

Sheet Data_Collections
A1: Collection | B1: Repo | C1: Rank | D1: Reason | E1: Description
A2: showcase | B2: RepoA | C2: 1 | D2: Strong showcase candidate. | E2: Best examples to show other people.

Sheet Data_Dimensions
A1: Repo | B1: Dimension | C1: Score | D1: Max Score | E1: Findings
A2: RepoA | B2: testing | C2: 0.9 | D2: 1 | E2: Healthy test coverage
A3: RepoA | B3: documentation | C3: 0.85 | D3: 1 | E3: README is strong
A4: RepoB | B4: testing | C4: 0.55 | D4: 1 | E4: A few test gaps remain
A5: RepoB | B5: release | C5: 0.48 | D5: 1 | E5: Checklist is incomplete
A6: RepoC | B6: security | C6: 0.22 | D6: 1 | E6: Security controls are missing
A7: RepoC | B7: testing | C7: 0.18 | D7: 1 | E7: No meaningful tests found

Sheet Data_Governance
A1: Repo | B1: Key | C1: Priority | D1: Title | E1: Expected Lift | F1: Effort | G1: Source | H1: Why

Sheet Data_History
A1: Series | B1: Run Index | C1: Score
A2: RepoA | B2: 1 | C2: 0.88
A3: RepoB | B3: 1 | C3: 0.62
A4: RepoC | B4: 1 | C4: 0.44
A5: __portfolio__ | B5: 1 | C5: 0.65

Sheet Data_ImplementationHotspots
A1: Repo | B1: Full Name | C1: Scope | D1: Path | E1: Module | F1: Category | G1: Pressure Score | H1: Suggestion Type | I1: Why It Matters | J1: Suggested First Move | K1: Signal Summary

Sheet Data_InterventionLedger
A1: Repo | B1: Latest Tier | C1: Latest Score | D1: Recent Intervention Count | E1: Last Intervention | F1: Pressure Trend | G1: Hotspot Persistence | H1: Scorecard Trend | I1: Campaign Follow Through | J1: Historical Intelligence Status | K1: Summary

Sheet Data_Lenses
A1: Repo | B1: Lens | C1: Score | D1: Orientation | E1: Summary | F1: Drivers
A2: RepoA | B2: ship_readiness | C2: 0.89 | E2: Ready
A3: RepoA | B3: momentum | C3: 0.75 | E3: Holding
A4: RepoA | B4: security_posture | C4: 0.82 | E4: Healthy
A5: RepoA | B5: portfolio_fit | C5: 0.86 | E5: Strong
A6: RepoB | B6: ship_readiness | C6: 0.63 | E6: Needs work
A7: RepoB | B7: momentum | C7: 0.54 | E7: Mixed
A8: RepoB | B8: security_posture | C8: 0.66 | E8: Watch
A9: RepoB | B9: portfolio_fit | C9: 0.58 | E9: Useful
A10: RepoC | B10: ship_readiness | C10: 0.42 | E10: Thin
A11: RepoC | B11: momentum | C11: 0.31 | E11: Fragile
A12: RepoC | B12: security_posture | C12: 0.28 | E12: Risky
A13: RepoC | B13: portfolio_fit | C13: 0.36 | E13: Questionable

Sheet Data_MaterialChangeRollups
A1: Repo | B1: Change Type | C1: Count | D1: Max Severity | E1: Sample Title
A2: RepoB | B2: reopened-review | C2: 1 | D2: 0 | E2: Release checklist reopened
A3: RepoC | B3: security-change | C3: 1 | D3: 0 | E3: Security posture needs attention

Sheet Data_OperatorOutcomes
A1: Metric | B1: Status | C1: Value | D1: Numerator | E1: Denominator | F1: Summary
A2: review_to_action_closure_rate | B2: insufficient-evidence
A3: median_runs_to_quiet_after_escalation | B3: insufficient-evidence
A4: repeated_regression_rate | B4: insufficient-evidence
A5: recommendation_validation_rate | B5: insufficient-evidence
A6: noisy_guidance_rate | B6: insufficient-evidence

Sheet Data_OperatorQueue
A1: Item ID | B1: Repo | C1: Kind | D1: Lane | E1: Priority | F1: Title | G1: Summary | H1: Recommended Action | I1: Source Run | J1: Age Days | K1: Links | L1: Follow-Through Age Runs | M1: Follow-Through Status | N1: Follow-Through Checkpoint Status | O1: Follow-Through Summary | P1: Follow-Through Last Touch | Q1: Follow-Through Next Checkpoint | R1: Follow-Through Evidence Hint | S1: Follow-Through Escalation Status | T1: Follow-Through Escalation Summary | U1: Follow-Through Escalation Reason | V1: Follow-Through Recovery Age Runs | W1: Follow-Through Recovery Status | X1: Follow-Through Recovery Summary | Y1: Follow-Through Recovery Reason | Z1: Follow-Through Recovery Persistence Age Runs | AA1: Follow-Through Recovery Persistence Status | AB1: Follow-Through Recovery Persistence Summary | AC1: Follow-Through Recovery Persistence Reason | AD1: Follow-Through Relapse Churn Status | AE1: Follow-Through Relapse Churn Summary | AF1: Follow-Through Relapse Churn Reason | AG1: Follow-Through Recovery Freshness Age Runs | AH1: Follow-Through Recovery Freshness Status | AI1: Follow-Through Recovery Freshness Summary | AJ1: Follow-Through Recovery Freshness Reason | AK1: Follow-Through Recovery Decay Status | AL1: Follow-Through Recovery Decay Summary | AM1: Follow-Through Recovery Decay Reason | AN1: Follow-Through Recovery Memory Reset Status | AO1: Follow-Through Recovery Memory Reset Summary | AP1: Follow-Through Recovery Memory Reset Reason | AQ1: Follow-Through Recovery Rebuild Strength Age Runs | AR1: Follow-Through Recovery Rebuild Strength Status | AS1: Follow-Through Recovery Rebuild Strength Summary | AT1: Follow-Through Recovery Rebuild Strength Reason | AU1: Follow-Through Recovery Reacquisition Status | AV1: Follow-Through Recovery Reacquisition Summary | AW1: Follow-Through Recovery Reacquisition Reason | AX1: Follow-Through Recovery Reacquisition Durability Age Runs | AY1: Follow-Through Recovery Reacquisition Durability Status | AZ1: Follow-Through Recovery Reacquisition Durability Summary | BA1: Follow-Through Recovery Reacquisition Durability Reason | BB1: Follow-Through Recovery Reacquisition Consolidation Status | BC1: Follow-Through Recovery Reacquisition Consolidation Summary | BD1: Follow-Through Recovery Reacquisition Consolidation Reason | BE1: Follow-Through Reacquisition Softening Decay Age Runs | BF1: Follow-Through Reacquisition Softening Decay Status | BG1: Follow-Through Reacquisition Softening Decay Summary | BH1: Follow-Through Reacquisition Softening Decay Reason | BI1: Follow-Through Reacquisition Confidence Retirement Status | BJ1: Follow-Through Reacquisition Confidence Retirement Summary | BK1: Follow-Through Reacquisition Confidence Retirement Reason | BL1: Follow-Through Reacquisition Revalidation Recovery Age Runs | BM1: Follow-Through Reacquisition Revalidation Recovery Status | BN1: Follow-Through Reacquisition Revalidation Recovery Summary | BO1: Follow-Through Reacquisition Revalidation Recovery Reason | BP1: Catalog Line | BQ1: Operating Path | BR1: Intent Alignment | BS1: Intent Alignment Reason | BT1: Scorecard Line | BU1: Maturity Gap Summary | BV1: Action Sync Stage | BW1: Action Sync Reason | BX1: Suggested Campaign | BY1: Suggested Writeback Target | BZ1: Action Sync Line | CA1: Apply Packet State | CB1: Apply Packet Summary | CC1: Apply Packet Command | CD1: Post-Apply State | CE1: Post-Apply Summary | CF1: Post-Apply Line | CG1: Campaign Tuning Status | CH1: Campaign Tuning Summary | CI1: Campaign Tuning Line | CJ1: Historical Intelligence Status | CK1: Historical Intelligence Summary | CL1: Historical Intelligence Line | CM1: Approval State | CN1: Approval Summary | CO1: Approval Line
B2: RepoC | C2: campaign | D2: blocked | E2: 1 | F2: Security drift needs review | G2: RepoC still needs a governance decision before the security review can settle. | H2: Open the governed control preview and decide whether to apply CodeQL. | J2: 0 | K2: [{"label": "GitHub Issue", "url": "https://github.com/sample-user/RepoC/issues/1"}] | L2: 0 | V2: 0 | Z2: 0 | AG2: 0 | AQ2: 0 | AX2: 0 | BE2: 0 | BL2: 0
B3: RepoB | C3: review | D3: urgent | E3: 2 | F3: Release checklist reopened | G3: RepoB needs a small release follow-through pass. | H3: Re-run the release checklist and close the missing item. | J3: 0 | K3: [] | L3: 0 | V3: 0 | Z3: 0 | AG3: 0 | AQ3: 0 | AX3: 0 | BE3: 0 | BL3: 0
B4: RepoA | C4: maintenance | D4: ready | E4: 3 | F4: Protect shipped momentum | G4: A small polish pass would keep the showcase repo strong. | H4: Tidy the release notes and publish the next small maintenance release. | J4: 0 | K4: [] | L4: 0 | V4: 0 | Z4: 0 | AG4: 0 | AQ4: 0 | AX4: 0 | BE4: 0 | BL4: 0
B5: RepoA | C5: cleanup | D5: deferred | E5: 4 | F5: Archive old brainstorm notes | G5: Backlog cleanup is optional this week. | H5: Leave this alone unless priorities change. | J5: 0 | K5: [] | L5: 0 | V5: 0 | Z5: 0 | AG5: 0 | AQ5: 0 | AX5: 0 | BE5: 0 | BL5: 0

Sheet Data_OperatorRepoRollups
A1: Repo | B1: Total Items | C1: Blocked | D1: Urgent | E1: Ready | F1: Deferred | G1: Primary Kind | H1: Top Priority | I1: Top Title | J1: Recommended Action
A2: RepoC | B2: 1 | C2: 1 | D2: 0 | E2: 0 | F2: 0 | G2: campaign | H2: 0 | I2: Security drift needs review | J2: Open the governed control preview and decide whether to apply CodeQL.
A3: RepoB | B3: 1 | C3: 0 | D3: 1 | E3: 0 | F3: 0 | G3: review | H3: 0 | I3: Release checklist reopened | J3: Re-run the release checklist and close the missing item.
A4: RepoA | B4: 2 | C4: 0 | D4: 0 | E4: 1 | F4: 1 | G4: maintenance | H4: 0 | I4: Archive old brainstorm notes | J4: Leave this alone unless priorities change.

Sheet Data_PortfolioCatalog
A1: Repo | B1: Full Name | C1: Owner | D1: Team | E1: Purpose | F1: Lifecycle | G1: Criticality | H1: Review Cadence | I1: Disposition | J1: Maturity Program | K1: Target Maturity | L1: Operating Path | M1: Path Override | N1: Path Confidence | O1: Notes | P1: Intent Alignment | Q1: Intent Alignment Reason | R1: Catalog Line
A2: RepoA | B2: sample-user/RepoA | P2: missing-contract
A3: RepoB | B3: sample-user/RepoB | P3: missing-contract
A4: RepoC | B4: sample-user/RepoC | P4: missing-contract

Sheet Data_PortfolioHistory
A1: Run Index | B1: Date | C1: Average Score | D1: Repos Audited | E1: Shipped | F1: Functional | G1: Security Avg | H1: Review Emitted | I1: Campaign Drift | J1: Governance Drift
A2: 1 | B2: 2026-04-12 | C2: 0.65 | D2: 3 | E2: 1 | F2: 1 | G2: 0.58 | H2: yes | I2: 1 | J2: 1

Sheet Data_RepoDetail
A1: Repo | B1: URL | C1: Language | D1: Description | E1: Overall Score | F1: Interest Score | G1: Grade | H1: Tier | I1: Badges | J1: Flags | K1: Collections | L1: Security Label | M1: Security Score | N1: Ship Lens Summary | O1: Momentum Lens Summary | P1: Security Lens Summary | Q1: Portfolio Fit Summary | R1: Trend Sparkline | S1: Top Positive Drivers | T1: Top Negative Drivers | U1: Next Tier Gap Summary | V1: Next Best Action | W1: Next Best Action Rationale | X1: Top Hotspot 1 | Y1: Top Hotspot 2 | Z1: Top Hotspot 3 | AA1: Top Action 1 | AB1: Top Action 2 | AC1: Top Action 3 | AD1: Last Movement | AE1: Recent Change Summary | AF1: Follow-Through Status | AG1: Follow-Through Summary | AH1: Checkpoint Timing | AI1: Escalation | AJ1: Escalation Summary | AK1: Recovery / Retirement | AL1: Recovery / Retirement Summary | AM1: Recovery Persistence | AN1: Recovery Persistence Summary | AO1: Relapse Churn | AP1: Relapse Churn Summary | AQ1: Recovery Freshness | AR1: Recovery Freshness Summary | AS1: Recovery Memory Reset | AT1: Recovery Memory Reset Summary | AU1: Recovery Rebuild Strength | AV1: Recovery Rebuild Strength Summary | AW1: Recovery Reacquisition | AX1: Recovery Reacquisition Summary | AY1: Reacquisition Durability | AZ1: Reacquisition Durability Summary | BA1: Reacquisition Confidence | BB1: Reacquisition Confidence Summary | BC1: Reacquisition Softening Decay | BD1: Reacquisition Softening Decay Summary | BE1: Reacquisition Confidence Retirement | BF1: Reacquisition Confidence Retirement Summary | BG1: Revalidation Recovery | BH1: Revalidation Recovery Summary | BI1: What Would Count As Progress | BJ1: Catalog | BK1: Operating Path | BL1: Intent Alignment | BM1: Scorecard | BN1: Maturity Gap | BO1: Where To Start Summary | BP1: Implementation Hotspot 1 | BQ1: Implementation Hotspot 2 | BR1: Implementation Hotspot 3
A2: RepoA | B2: https://github.com/sample-user/RepoA | C2: Python | D2: A polished shipped project. | E2: 0.88 | F2: 0.61 | G2: A | H2: shipped | I2: fresh, tested | J2: None | K2: showcase | L2: healthy | M2: 0.82 | N2: Ready | O2: Holding | P2: Healthy | Q2: Strong | S2: Testing (0.90), Documentation (0.85), Security (0.82) | T2: Security (0.82), Documentation (0.85), Testing (0.90) | U2: Already at shipped tier; focus on protecting momentum and preventing drift. | V2: Tidy the release notes and publish the next small maintenance release. | W2: No action rationale is recorded yet. | X2: Keep release notes fresh | Y2: No secondary hotspot recorded yet. | Z2: No third hotspot recorded yet. | AA2: Tidy the release notes and publish the next small maintenance release. | AB2: No second action candidate recorded yet. | AC2: No third action candidate recorded yet. | AD2: Current run | AE2: A small polish pass would keep the showcase repo strong. | AF2: Unknown | AG2: No follow-through evidence is recorded yet. | AH2: Unknown | AI2: Unknown | AJ2: No stronger follow-through escalation is currently surfaced. | AK2: None | AL2: No follow-through recovery or escalation-retirement signal is currently surfaced. | AM2: None | AN2: No follow-through recovery persistence signal is currently surfaced. | AO2: None | AP2: No relapse churn is currently surfaced. | AQ2: None | AR2: No follow-through recovery freshness signal is currently surfaced. | AS2: None | AT2: No follow-through recovery memory reset signal is currently surfaced. | AU2: None | AV2: No follow-through recovery rebuild-strength signal is currently surfaced. | AW2: None | AX2: No follow-through recovery reacquisition signal is currently surfaced. | AY2: None | AZ2: No follow-through reacquisition durability signal is currently surfaced. | BA2: None | BB2: No follow-through reacquisition confidence-consolidation signal is currently surfaced. | BC2: None | BD2: No reacquisition softening-decay signal is currently surfaced. | BE2: None | BF2: No reacquisition confidence-retirement signal is currently surfaced. | BG2: None | BH2: No post-revalidation recovery or confidence re-earning signal is currently surfaced. | BI2: Use the next run or linked artifact to confirm whether the recommendation moved. | BJ2: No portfolio catalog contract is recorded yet. | BK2: Operating Path: Unspecified (legacy confidence) — No operating-path rationale is recorded yet. | BL2: missing-contract: Intent alignment cannot be judged until a portfolio catalog contract exists. | BM2: Scorecard: No maturity scorecard is recorded yet. | BN2: No maturity gap summary is recorded yet. | BO2: No meaningful implementation hotspot is currently surfaced. | BP2: No implementation hotspot is currently surfaced. | BQ2: No second implementation hotspot is currently surfaced. | BR2: No third implementation hotspot is currently surfaced. | BS2: — | BT2: — | BU2: — | BV2: — | BW2: No | BX2: — | BY2: — | BZ2: — | CA2: —
A3: RepoB | B3: https://github.com/sample-user/RepoB | C3: TypeScript | D3: A functional project with follow-through left to do. | E3: 0.62 | F3: 0.37 | G3: C | H3: functional | I3: None | J3: release-checklist-open | K3: — | L3: watch | M3: 0.66 | N3: Needs work | O3: Mixed | P3: Watch | Q3: Useful | S3: Security (0.66), Testing (0.55), Release (0.48) | T3: Release (0.48), Testing (0.55), Security (0.66) | U3: Needs +0.13 to reach shipped. | V3: Re-run the release checklist and close the missing item. | W3: No action rationale is recorded yet. | X3: Finish release checklist | Y3: No secondary hotspot recorded yet. | Z3: No third hotspot recorded yet. | AA3: Re-run the release checklist and close the missing item. | AB3: No second action candidate recorded yet. | AC3: No third action candidate recorded yet. | AD3: Current run | AE3: RepoB needs a small release follow-through pass. | AF3: Unknown | AG3: No follow-through evidence is recorded yet. | AH3: Unknown | AI3: Unknown | AJ3: No stronger follow-through escalation is currently surfaced. | AK3: None | AL3: No follow-through recovery or escalation-retirement signal is currently surfaced. | AM3: None | AN3: No follow-through recovery persistence signal is currently surfaced. | AO3: None | AP3: No relapse churn is currently surfaced. | AQ3: None | AR3: No follow-through recovery freshness signal is currently surfaced. | AS3: None | AT3: No follow-through recovery memory reset signal is currently surfaced. | AU3: None | AV3: No follow-through recovery rebuild-strength signal is currently surfaced. | AW3: None | AX3: No follow-through recovery reacquisition signal is currently surfaced. | AY3: None | AZ3: No follow-through reacquisition durability signal is currently surfaced. | BA3: None | BB3: No follow-through reacquisition confidence-consolidation signal is currently surfaced. | BC3: None | BD3: No reacquisition softening-decay signal is currently surfaced. | BE3: None | BF3: No reacquisition confidence-retirement signal is currently surfaced. | BG3: None | BH3: No post-revalidation recovery or confidence re-earning signal is currently surfaced. | BI3: Use the next run or linked artifact to confirm whether the recommendation moved. | BJ3: No portfolio catalog contract is recorded yet. | BK3: Operating Path: Unspecified (legacy confidence) — No operating-path rationale is recorded yet. | BL3: missing-contract: Intent alignment cannot be judged until a portfolio catalog contract exists. | BM3: Scorecard: No maturity scorecard is recorded yet. | BN3: No maturity gap summary is recorded yet. | BO3: No meaningful implementation hotspot is currently surfaced. | BP3: No implementation hotspot is currently surfaced. | BQ3: No second implementation hotspot is currently surfaced. | BR3: No third implementation hotspot is currently surfaced. | BS3: — | BT3: — | BU3: — | BV3: — | BW3: No | BX3: — | BY3: — | BZ3: — | CA3: —
A4: RepoC | B4: https://github.com/sample-user/RepoC | C4: Python | D4: A risky work-in-progress project. | E4: 0.44 | F4: 0.16 | G4: D | H4: wip | I4: None | J4: no-tests, security-review | K4: — | L4: critical | M4: 0.28 | N4: Thin | O4: Fragile | P4: Risky | Q4: Questionable | S4: Security (0.28), Testing (0.18) | T4: Testing (0.18), Security (0.28) | U4: Needs +0.31 to reach shipped. | V4: Open the governed control preview and decide whether to apply CodeQL. | W4: No action rationale is recorded yet. | X4: Security posture needs attention | Y4: No secondary hotspot recorded yet. | Z4: No third hotspot recorded yet. | AA4: Open the governed control preview and decide whether to apply CodeQL. | AB4: No second action candidate recorded yet. | AC4: No third action candidate recorded yet. | AD4: Current run | AE4: RepoC still needs a governance decision before the security review can settle. | AF4: Unknown | AG4: No follow-through evidence is recorded yet. | AH4: Unknown | AI4: Unknown | AJ4: No stronger follow-through escalation is currently surfaced. | AK4: None | AL4: No follow-through recovery or escalation-retirement signal is currently surfaced. | AM4: None | AN4: No follow-through recovery persistence signal is currently surfaced. | AO4: None | AP4: No relapse churn is currently surfaced. | AQ4: None | AR4: No follow-through recovery freshness signal is currently surfaced. | AS4: None | AT4: No follow-through recovery memory reset signal is currently surfaced. | AU4: None | AV4: No follow-through recovery rebuild-strength signal is currently surfaced. | AW4: None | AX4: No follow-through recovery reacquisition signal is currently surfaced. | AY4: None | AZ4: No follow-through reacquisition durability signal is currently surfaced. | BA4: None | BB4: No follow-through reacquisition confidence-consolidation signal is currently surfaced. | BC4: None | BD4: No reacquisition softening-decay signal is currently surfaced. | BE4: None | BF4: No reacquisition confidence-retirement signal is currently surfaced. | BG4: None | BH4: No post-revalidation recovery or confidence re-earning signal is currently surfaced. | BI4: Use the next run or linked artifact to confirm whether the recommendation moved. | BJ4: No portfolio catalog contract is recorded yet. | BK4: Operating Path: Unspecified (legacy confidence) — No operating-path rationale is recorded yet. | BL4: missing-contract: Intent alignment cannot be judged until a portfolio catalog contract exists. | BM4: Scorecard: No maturity scorecard is recorded yet. | BN4: No maturity gap summary is recorded yet. | BO4: No meaningful implementation hotspot is currently surfaced. | BP4: No implementation hotspot is currently surfaced. | BQ4: No second implementation hotspot is currently surfaced. | BR4: No third implementation hotspot is currently surfaced. | BS4: — | BT4: — | BU4: — | BV4: — | BW4: No | BX4: — | BY4: — | BZ4: — | CA4: —

Sheet Data_RepoDimensionRollups
A1: Lookup Key | B1: Repo | C1: Rank | D1: Dimension | E1: Score | F1: Summary
A2: RepoA::1 | B2: RepoA | C2: 1 | D2: documentation | E2: 0.85 | F2: README is strong
A3: RepoA::2 | B3: RepoA | C3: 2 | D3: testing | E3: 0.9 | F3: Healthy test coverage
A4: RepoB::1 | B4: RepoB | C4: 1 | D4: release | E4: 0.48 | F4: Checklist is incomplete
A5: RepoB::2 | B5: RepoB | C5: 2 | D5: testing | E5: 0.55 | F5: A few test gaps remain
A6: RepoC::1 | B6: RepoC | C6: 1 | D6: testing | E6: 0.18 | F6: No meaningful tests found
A7: RepoC::2 | B7: RepoC | C7: 2 | D7: security | E7: 0.22 | F7: Security controls are missing

Sheet Data_RepoHistoryRollups
A1: Repo | B1: Run Index | C1: Score | D1: Sparkline
A2: RepoA | B2: 1 | C2: 0.88
A3: RepoB | B3: 1 | C3: 0.62
A4: RepoC | B4: 1 | C4: 0.44

Sheet Data_Repos
A1: Repo | B1: Full Name | C1: Language | D1: Private | E1: Archived | F1: Overall Score | G1: Interest Score | H1: Grade | I1: Tier | J1: Security Label | K1: Collections | L1: Ship Readiness | M1: Maintenance Risk | N1: Showcase Value | O1: Security Posture | P1: Momentum | Q1: Portfolio Fit
A2: RepoA | B2: sample-user/RepoA | C2: Python | D2: No | E2: No | F2: 0.88 | G2: 0.61 | H2: A | I2: shipped | J2: healthy | K2: showcase | L2: 0.89 | M2: 0 | N2: 0 | O2: 0.82 | P2: 0.75 | Q2: 0.86
A3: RepoB | B3: sample-user/RepoB | C3: TypeScript | D3: No | E3: No | F3: 0.62 | G3: 0.37 | H3: C | I3: functional | J3: watch | L3: 0.63 | M3: 0 | N3: 0 | O3: 0.66 | P3: 0.54 | Q3: 0.58
A4: RepoC | B4: sample-user/RepoC | C4: Python | D4: No | E4: No | F4: 0.44 | G4: 0.16 | H4: D | I4: wip | J4: critical | L4: 0.42 | M4: 0 | N4: 0 | O4: 0.28 | P4: 0.31 | Q4: 0.36

Sheet Data_ReviewHistory
A1: Review ID | B1: Source Run | C1: Generated | D1: Materiality | E1: Changes | F1: Status | G1: Decision State | H1: Sync State | I1: Safe To Defer | J1: Emitted
A2: sample-review-1 | C2: 2026-04-12T12:00:00+00:00 | E2: 2 | F2: open | G2: needs-review | H2: local-only | I2: no | J2: yes

Sheet Data_ReviewTargets
A1: Repo | B1: Title | C1: Severity | D1: Next Step | E1: Decision Hint | F1: Safe To Defer
A2: RepoC | B2: Security posture needs attention | C2: 0.84 | D2: Preview governance controls | E2: ready-for-governance-approval | F2: no

Sheet Data_Rollups
A1: Profile | B1: Collection | C1: Lens | D1: Repo Count | E1: Average Lens Score | F1: Top Repo | G1: Top Profile Score
A2: default | B2: all | C2: ship_readiness | D2: 3 | E2: 0.647 | F2: RepoA | G2: 0.88
A3: default | B3: all | C3: showcase_value | D3: 3 | E3: 0 | F3: RepoA | G3: 0.88
A4: default | B4: showcase | C4: ship_readiness | D4: 1 | E4: 0.89 | F4: RepoA | G4: 0.88
A5: default | B5: showcase | C5: showcase_value | D5: 1 | E5: 0 | F5: RepoA | G5: 0.88

Sheet Data_RunChangeRepoData
A1: Section | B1: Repo | C1: Delta | D1: Old Tier | E1: New Tier | F1: Security | G1: Hotspots | H1: Collections | I1: Summary
A2: repo-change | B2: RepoA | C2: 0.09 | D2: functional | E2: shipped | F2: healthy | G2: 1 | H2: showcase | I2: General repo movement since the previous run.
A3: repo-change | B3: RepoC | C3: -0.08 | D3: functional | E3: wip | F3: critical | G3: 1 | I3: General repo movement since the previous run.
A4: tier-promotion | B4: RepoA | C4: 0.09 | D4: functional | E4: shipped | I4: Tier promotion detected in the comparison window.
A5: tier-demotion | B5: RepoC | C5: -0.08 | D5: functional | E5: wip | I5: Tier demotion detected in the comparison window.
A6: material-security-change | B6: RepoC | C6: 0.84 | I6: Security posture needs attention
A7: material-reopened-review | B7: RepoB | C7: 0.51 | I7: Release checklist reopened

Sheet Data_RunChangeRollups
A1: Metric | B1: Value | C1: Summary
A2: Summary | B2: Average score moved +0.020; 0 meaningful improvements, 0 regressions, 1 promotions, and 1 demotions were recorded.
A3: Score Improvements | B3: 0 | C3: Repos that improved since the last run.
A4: Score Regressions | B4: 0 | C4: Repos that regressed since the last run.
A5: Tier Promotions | B5: 1 | C5: Repos that moved up a tier.
A6: Tier Demotions | B6: 1 | C6: Repos that moved down a tier.
A7: New Repos | B7: 0 | C7: Repos that are new in this run.
A8: Removed Repos | B8: 0 | C8: Repos missing compared with the prior run.
A9: Security Changes | B9: 1 | C9: Repos with security posture movement.
A10: Governance Changes | B10: 1 | C10: Repos with collection or governance drift.
A11: Notable Repo Changes | B11: 2 | C11: Repos with notable diff rows.

Sheet Data_Scenarios
A1: Key | B1: Title | C1: Lens | D1: Repo Count | E1: Average Expected Lens Delta | F1: Projected Tier Promotions
A2: testing | B2: Strengthen tests | C2: ship_readiness | D2: 2 | E2: 0.09 | F2: 1
A3: portfolio_projection | B3: Portfolio projection | C3: portfolio_fit | D3: 0 | E3: 0.05 | F3: 0

Sheet Data_Scorecards
A1: Repo | B1: Full Name | C1: Program | D1: Program Label | E1: Score | F1: Maturity Level | G1: Target Maturity | H1: Status | I1: Passed Rules | J1: Applicable Rules | K1: Failed Rule Keys | L1: Top Gaps | M1: Summary
A2: RepoA | B2: sample-user/RepoA | E2: 0 | I2: 0 | J2: 0
A3: RepoB | B3: sample-user/RepoB | E3: 0 | I3: 0 | J3: 0
A4: RepoC | B4: sample-user/RepoC | E4: 0 | I4: 0 | J4: 0

Sheet Data_Security
A1: Repo | B1: Label | C1: Score | D1: Secrets | E1: Dangerous Files | F1: SECURITY.md | G1: Dependabot | H1: Evidence
A2: RepoA | B2: healthy | C2: 0.82 | D2: 0 | E2: 0 | F2: No | G2: No
A3: RepoB | B3: watch | C3: 0.66 | D3: 0 | E3: 0 | F3: No | G3: No
A4: RepoC | B4: critical | C4: 0.28 | D4: 0 | E4: 0 | F4: No | G4: No

Sheet Data_SecurityAlerts
A1: Repo | B1: Alert Type | C1: Open Count | D1: Status
A2: RepoA | B2: code_scanning | C2: 0 | D2: unavailable
A3: RepoA | B3: secret_scanning | C3: 0 | D3: unavailable
A4: RepoB | B4: code_scanning | C4: 0 | D4: unavailable
A5: RepoB | B5: secret_scanning | C5: 0 | D5: unavailable
A6: RepoC | B6: code_scanning | C6: 0 | D6: unavailable
A7: RepoC | B7: secret_scanning | C7: 0 | D7: unavailable

Sheet Data_SecurityControls
A1: Repo | B1: Control | C1: Status | D1: Source | E1: Details
A2: RepoA | B2: security_md | C2: missing | D2: local
A3: RepoA | B3: dependabot_config | C3: missing | D3: local
A4: RepoA | B4: dependency_graph | C4: unavailable | D4: github | E4: None
A5: RepoA | B5: sbom_export | C5: unavailable | D5: github | E5: None
A6: RepoA | B6: code_scanning | C6: unavailable | D6: github | E6: None
A7: RepoA | B7: secret_scanning | C7: unavailable | D7: github | E7: None
A8: RepoB | B8: security_md | C8: missing | D8: local
A9: RepoB | B9: dependabot_config | C9: missing | D9: local
A10: RepoB | B10: dependency_graph | C10: unavailable | D10: github | E10: None
A11: RepoB | B11: sbom_export | C11: unavailable | D11: github | E11: None
A12: RepoB | B12: code_scanning | C12: unavailable | D12: github | E12: None
A13: RepoB | B13: secret_scanning | C13: unavailable | D13: github | E13: None
A14: RepoC | B14: security_md | C14: missing | D14: local
A15: RepoC | B15: dependabot_config | C15: missing | D15: local
A16: RepoC | B16: dependency_graph | C16: unavailable | D16: github | E16: None
A17: RepoC | B17: sbom_export | C17: unavailable | D17: github | E17: None
A18: RepoC | B18: code_scanning | C18: unavailable | D18: github | E18: None
A19: RepoC | B19: secret_scanning | C19: unavailable | D19: github | E19: None

Sheet Data_SecurityProviders
A1: Repo | B1: Provider | C1: Available | D1: Score | E1: Reason

Sheet Data_TrendMatrix
A1: Repo | B1: Run 1 | C1: Run 2 | D1: Run 3 | E1: Run 4 | F1: Run 5 | G1: Run 6 | H1: Run 7 | I1: Run 8 | J1: Run 9 | K1: Run 10 | L1: Run 11 | M1: Run 12
A2: RepoA | M2: 0.88
A3: RepoB | M3: 0.62
A4: RepoC | M4: 0.44

Sheet Data_Writeback
A1: Repo | B1: Target | C1: Status | D1: URL | E1: Before | F1: After
A2: sample-user/RepoC | B2: github-issue | C2: created | D2: https://github.com/sample-user/RepoC/issues/1 | E2: {} | F2: {}

Sheet Dep Graph
A1: Shared Dependencies (0 across 2+ repos)
A2: Dependency | B2: Repo Count | C2: Repos Using It

Sheet Governance Audit
A1: Governance Audit
A2: Evidence summary for approval age, fingerprint drift, rollback coverage, and applied results.
A4: Control | B4: Value
A5: Status | B5: Drifted
A6: Headline | B6: Governed security drift needs review.
A7: Approval Status | B7: Preview only
A8: Needs Re-Approval | B8: no
A9: Approval Age (days) | B9: —
A10: Fingerprint Mismatch | B10: no
A11: Applyable Count | B11: 1
A12: Drift Count | B12: 1
A13: Applied Count | B13: 0
A14: Rollback Available | B14: 1
A15: Selected View | B15: all

Sheet Hotspots
A1: Repo | B1: Category | C1: Severity | D1: Title | E1: Summary | F1: Recommended Action | G1: Tier

Sheet Initiative Tracker
A1: Initiative Tracker
A2: Tier-upgrade initiatives grouped by status: overdue · at-risk · on-track · met.
A3: No initiatives yet. Use `audit triage --set-initiative REPO --target-tier N --deadline YYYY-MM-DD`.

Sheet Lookups
A1: Type | B1: Key | C1: Value
A2: lens | B2: ship_readiness | C2: Delivery readiness
A3: lens | B3: showcase_value | C3: Story and polish
A4: profile | B4: default | C4: Balanced portfolio scoring.
A5: tier | B5: shipped | C5: 1
A6: tier | B6: functional | C6: 1
A7: tier | B7: wip | C7: 1
A8: tier | B8: skeleton | C8: 0
A9: tier | B9: abandoned | C9: 0
A10: repo-selector | B10: RepoA | C10: RepoA
A11: repo-selector | B11: RepoB | C11: RepoB
A12: repo-selector | B12: RepoC | C12: RepoC

Sheet Portfolio Catalog
A1: Portfolio Catalog
A2: Use this sheet to see what each repo is supposed to be, who owns it, and whether its current state still matches that intent.
A3: No portfolio catalog contract is recorded yet.
A4: Intent alignment cannot be judged until a portfolio catalog contract exists.
A5: No normalized operating-path contract is recorded yet.
A7: Repo | B7: Owner | C7: Team | D7: Purpose | E7: Lifecycle | F7: Criticality | G7: Review Cadence | H7: Disposition | I7: Maturity Program | J7: Target Maturity | K7: Operating Path | L7: Path Override | M7: Path Confidence | N7: Intent Alignment | O7: Notes
A8: RepoA | E8: — | F8: — | G8: — | H8: — | I8: — | J8: — | K8: — | L8: — | M8: — | N8: missing-contract | O8: —
A9: RepoB | E9: — | F9: — | G9: — | H9: — | I9: — | J9: — | K9: — | L9: — | M9: — | N9: missing-contract | O9: —
A10: RepoC | E10: — | F10: — | G10: — | H10: — | I10: — | J10: — | K10: — | L10: — | M10: — | N10: missing-contract | O10: —

Sheet Quick Wins
A1: Quick Wins — 2 repos near the next tier
A3: Repo | B3: Grade | C3: Current | D3: Score | E3: Next Tier | F3: Gap | G3: Top Actions | H3: Badges
A4: RepoC | B4: D | C4: wip | D4: 0.44 | E4: functional | F4: 0.11 | G4: Improve testing (0.2); Improve security (0.2) | H4: 0
A5: RepoB | B5: C | C5: functional | D5: 0.62 | E5: shipped | F5: 0.13 | G5: Improve release (0.5); Improve testing (0.6) | H5: 0

Sheet Repo Profiles
B1: RepoA | C1: RepoB | D1: RepoC
A2: README | B2: 0 | C2: 0 | D2: 0
A3: Structure | B3: 0 | C3: 0 | D3: 0
A4: Code Quality | B4: 0 | C4: 0 | D4: 0
A5: Testing | B5: 0.9 | C5: 0.55 | D5: 0.18
A6: CI/CD | B6: 0 | C6: 0 | D6: 0
A7: Deps | B7: 0 | C7: 0 | D7: 0
A8: Activity | B8: 0 | C8: 0 | D8: 0
A9: Docs | B9: 0.85 | C9: 0 | D9: 0
A10: Build Ready | B10: 0 | C10: 0 | D10: 0
A11: Community | B11: 0 | C11: 0 | D11: 0

Sheet Review History
A1: Review History
A2: Use this ledger to see which recurring review is active now and how prior review runs were resolved, deferred, or left local-only.
A4: Current State
A5: Current Review | B5: sample-review-1
A6: Current Status | B6: open
A7: History Rows | B7: 1
A8: How To Read This | B8: The active review is summarized above; the ledger below is the historical trail.
A9: Review ID | B9: Generated | C9: Changes | D9: Status | E9: Decision State | F9: Sync State | G9: Emitted
A10: sample-review-1 | B10: 2026-04-12T12:00:00+00:00 | C10: 2 | D10: open | E10: needs-review | F10: local-only | G10: yes

Sheet Scenario Planner
A1: Scenario Planner
A2: Profile: default
A3: Collection: all
A5: Lever | B5: Lens | C5: Repo Count | D5: Avg Lift | E5: Weighted Impact | F5: Projected Promotions
A6: Publish the next maintenance release | C6: 1 | D6: 0 | E6: 0 | F6: 0
A7: Close the reopened release item | C7: 1 | D7: 0 | E7: 0 | F7: 0
A8: Preview governance controls | C8: 1 | D8: 0 | E8: 0 | F8: 0
A10: Selected Repos | B10: 3
A11: Projected Avg Score Delta | B11: 0
A12: Projected Promotions | B12: 0

Sheet Score Explainer
A1: Scoring System Reference
A3: Dimension Weights
A4: Dimension | B4: Weight | C4: What It Measures | D4: How to Improve
A5: testing | B5: 18% | C5: Test directories, framework, test file count | D5: Add test/ with pytest/jest/vitest configured
A6: code_quality | B6: 15% | C6: Entry points, TODO density, types, commit quality | D6: Add main entry point, reduce TODOs
A7: activity | B7: 15% | C7: Push recency, commit count, releases, bus factor | D7: Push regularly, tag releases
A8: readme | B8: 12% | C8: Exists, description, install instructions, examples | D8: Add usage section with code blocks
A9: structure | B9: 10% | C9: .gitignore, source dirs, config files, LICENSE | D9: Add .gitignore + LICENSE + package manifest
A10: cicd | B10: 10% | C10: GitHub Actions, CI configs, build scripts | D10: Add .github/workflows/ci.yml
A11: dependencies | B11: 8% | C11: Manifest + lockfile, dep count, libyears | D11: Add lockfile alongside manifest
A12: build_readiness | B12: 7% | C12: Docker, Makefile, .env.example, deploy configs | D12: Add Dockerfile or Makefile
A13: community_profile | B13: 3% | C13: LICENSE, CONTRIBUTING, CODE_OF_CONDUCT | D13: Add CONTRIBUTING.md
A14: documentation | B14: 2% | C14: docs/ dir, CHANGELOG, comment density | D14: Add docs/ folder or CHANGELOG.md
A16: Grade Thresholds
A17: A | B17: >= 80%
A18: B | B18: >= 70%
A19: C | B19: >= 55%
A20: D | B20: >= 35%
A21: F | B21: >= 0%
A23: Tier Thresholds
A24: Shipped | B24: >= 75%
A25: Functional | B25: >= 55%
A26: Wip | B26: >= 35%
A27: Skeleton | B27: >= 15%
A28: Abandoned | B28: >= 0%

Sheet Scorecards
A1: Scorecards
A2: Use this sheet to compare each repo against the maturity bar that matches its intended role.
A3: No maturity scorecard is recorded yet.
A5: Repo | B5: Program | C5: Maturity | D5: Target | E5: Status | F5: Score | G5: Top Gaps | H5: Summary
A6: RepoA | B6: — | C6: — | D6: — | E6: — | F6: 0 | G6: — | H6: —
A7: RepoB | B7: — | C7: — | D7: — | E7: — | F7: 0 | G7: — | H7: —
A8: RepoC | B8: — | C8: — | D8: — | E8: — | F8: 0 | G8: — | H8: —

Sheet Scoring Heatmap
A1: Repo | B1: Grade | C1: Overall | D1: Readme | E1: Structure | F1: Code Quality | G1: Testing | H1: Cicd | I1: Dependencies | J1: Activity | K1: Documentation | L1: Build Readiness | M1: Community Profile | N1: Interest
A2: RepoA | B2: A | C2: 0.88 | D2: 0 | E2: 0 | F2: 0 | G2: 0.9 | H2: 0 | I2: 0 | J2: 0 | K2: 0.85 | L2: 0 | M2: 0 | N2: 0
A3: RepoB | B3: C | C3: 0.62 | D3: 0 | E3: 0 | F3: 0 | G3: 0.55 | H3: 0 | I3: 0 | J3: 0 | K3: 0 | L3: 0 | M3: 0 | N3: 0
A4: RepoC | B4: D | C4: 0.44 | D4: 0 | E4: 0 | F4: 0 | G4: 0.18 | H4: 0 | I4: 0 | J4: 0 | K4: 0 | L4: 0 | M4: 0 | N4: 0

Sheet Security
A1: Repo | B1: Score | C1: Secrets | D1: Dangerous Files | E1: SECURITY.md | F1: Dependabot | G1: GitHub | H1: Findings | I1: Dep Critical | J1: Dep High | K1: CodeQL Critical | L1: CodeQL High | M1: Secrets Open | N1: OSSF Score
A2: RepoC | B2: 0.28 | C2: 0 | E2: No | F2: No | G2: No | I2: — | J2: — | K2: — | L2: — | M2: — | N2: —
A3: RepoB | B3: 0.66 | C3: 0 | E3: No | F3: No | G3: No | I3: — | J3: — | K3: — | L3: — | M3: — | N3: —
A4: RepoA | B4: 0.82 | C4: 0 | E4: No | F4: No | G4: No | I4: — | J4: — | K4: — | L4: — | M4: — | N4: —

Sheet Security Controls
A1: Repo | B1: SECURITY.md | C1: Dependabot | D1: Dependency Graph | E1: SBOM | F1: Code Scanning | G1: Secret Scanning
A2: RepoC | B2: No | C2: No | D2: unavailable | E2: unavailable | F2: unavailable | G2: unavailable
A3: RepoB | B3: No | C3: No | D3: unavailable | E3: unavailable | F3: unavailable | G3: unavailable
A4: RepoA | B4: No | C4: No | D4: unavailable | E4: unavailable | F4: unavailable | G4: unavailable

Sheet Security Debt
A1: Repo | B1: Priority | C1: Action | D1: Expected Lift | E1: Effort | F1: Source
A2: RepoC | B2: high | C2: Enable CodeQL default setup | D2: 0.12 | E2: medium | F2: github

Sheet Supply Chain
A1: Repo | B1: Security Score | C1: Dependency Graph | D1: SBOM | E1: Scorecard | F1: Top Recommendation
A2: RepoC | B2: 0.28 | C2: unavailable | D2: unavailable
A3: RepoB | B3: 0.66 | C3: unavailable | D3: unavailable
A4: RepoA | B4: 0.82 | C4: unavailable | D4: unavailable

Sheet TemplateInfo
A1: Workbook Mode | B1: standard
A2: Review Open Count | B2: 1
A3: Review Deferred Count | B3: 0
A4: Review Resolved Count | B4: 0
A5: Campaign Action Count | B5: 1
A6: Campaign Repo Count | B6: 1
A7: Governance Ready Count | B7: 1
A8: Governance Drift Count | B8: 1
A9: Latest Portfolio Grade | B9: B
A10: Latest Average Score | B10: 0.65
A11: Latest Review State | B11: open
A12: Selected Profile | B12: default
A13: Selected Collection | B13: all

Sheet Tier Breakdown
A1: SHIPPED (1 repos)
A2: Repo | B2: Grade | C2: Score | D2: Language | E2: Badges | F2: Description
A3: RepoA | B3: A | C3: 0.88 | D3: Python | E3: 2 | F3: A polished shipped project.
A6: FUNCTIONAL (1 repos)
A7: Repo | B7: Grade | C7: Score | D7: Language | E7: Badges | F7: Description
A8: RepoB | B8: C | C8: 0.62 | D8: TypeScript | E8: 0 | F8: A functional project with follow-through left to d
A11: WIP (1 repos)
A12: Repo | B12: Grade | C12: Score | D12: Language | E12: Badges | F12: Description
A13: RepoC | B13: D | C13: 0.44 | D13: Python | E13: 0 | F13: A risky work-in-progress project.

Sheet Trends
A1: Portfolio Trends
A3: Run more audits to see trends (need 2+ historical runs)

Sheet Writeback Audit
A1: Writeback Audit
A2: This sheet summarizes writeback outcomes and rollback confidence without mutating anything by itself.
A4: Current Writeback State | E4: Action Sync Readiness
A5: Writeback Rows | B5: 1 | E5: Action Sync Readiness | F5: No current campaign needs Action Sync yet, so the safest next move is to keep the story local.
A6: Rollback Ready | B6: 0 | E6: Next Action Sync Step | F6: Stay local for now; no current campaign needs preview or apply.
A7: Created / Updated / Closed | B7: 1 / 0 / 0 | E7: Apply Packet | F7: No current campaign has a safe execution handoff yet, so the local story should stay local for now.
E8: Command Hint | F8: No Action Sync command is recommended yet.
E9: Post-Apply Monitoring | F9: No recent Action Sync apply needs post-apply monitoring yet, so the local weekly story can stay local.
A10: Repo | B10: Target | C10: Status | D10: Rollback | E10: URL | F10: Details
A11: sample-user/RepoC | B11: github-issue | C11: created | D11: partial | E11: https://github.com/sample-user/RepoC/issues/1 | F11: {"repo_full_name": "sample-user/RepoC", "target": "github-issue", "status": "created", "url": "https://github.com/sample-user/RepoC/issues/1"}
E12: Next Tie-Break Candidate | F12: No current campaign needs a tuning tie-break yet.
E13: Historical Portfolio Intelligence | F13: Historical portfolio intelligence is still thin, so the weekly story should stay grounded in the current run and recent operator queue.
E14: Next Historical Focus | F14: Stay local for now; no repo has enough cross-run intervention evidence to demand a historical follow-up read yet.
E15: Automation Guidance | F15: Automation guidance stays quiet until a campaign has a clearly safe preview, follow-up, or manual-only posture.
E16: Next Safe Automation Step | F16: Stay local for now; no current campaign has a stronger safe automation posture than manual review.
E17: Approval Workflow | F17: No current approval needs review yet, so the approval workflow can stay local for now.
E18: Next Approval Review | F18: Stay local for now; no current approval needs review.
